[
	{
		"text": "Kannte ihn vor #rbtv nicht, aber ich merke:Je \u00f6fter ich den @Colin_Gaebel sehe, desto mehr mag ich ihn :)\nDanke f\u00fcr den tollen Abend, Colin!",
		"created_at": 1432936826,
		"user": {
			"id": "3021707842",
			"name": "Tweeplunder"
		},
		"retweet_count": 0,
		"id": "604406973329756160",
		"favorite_count": 6
	},
	{
		"text": "@TheRocketBeans macht ihr auch mal wieder ein Brett &amp; Breakfast? ist lange her :-( #rbtv",
		"created_at": 1432936996,
		"user": {
			"id": "2730027929",
			"name": "unewyear"
		},
		"retweet_count": 0,
		"id": "604407688701693952",
		"favorite_count": 2
	},
	{
		"text": "@Katie_May_05 vielen dank f\u00fcr die sch\u00f6ne Zeit mit dir :) du warst klasse ;) viel erfolg weiterhin... machs gut :) :( #rbtv #timetosaygoodbye",
		"created_at": 1432937026,
		"user": {
			"id": "3065689835",
			"name": "rbMeriton"
		},
		"retweet_count": 0,
		"id": "604407812047945728",
		"favorite_count": 0
	},
	{
		"text": "@Lime7ime Alles Gute zum Burzeltag!!!! #rbtv",
		"created_at": 1432937037,
		"user": {
			"id": "317430628",
			"name": "Sense030_"
		},
		"retweet_count": 0,
		"id": "604407860093718528",
		"favorite_count": 1
	},
	{
		"text": "Thx dass du bei #rbtv warst @Katie_May_05 ! Alles Gute und Erfolg in deinem weiteren Werdegang! #beansneverwalkalone #einmalbohneimmerbohne",
		"created_at": 1432937291,
		"user": {
			"id": "2994652739",
			"name": "zeroin009"
		},
		"retweet_count": 0,
		"id": "604408923219726337",
		"favorite_count": 0
	},
	{
		"text": "@EtienneToGo @TheRocketBeans Der k\u00f6nnte Mr. Laser ein Konkurrent werde. Klasse trashiger Kurzfilm #rbtv\nhttps://t.co/85MhAN7NCl",
		"created_at": 1432937409,
		"user": {
			"id": "2729364224",
			"name": "sel4more"
		},
		"retweet_count": 0,
		"id": "604409418734792704",
		"favorite_count": 0
	},
	{
		"text": "passend zu #rbtv #rocketbeats traum-mixtape \"hab ichs mic check ich moves wie eddie in tekken 3\" (deiner tracks 2) https://t.co/tz8T6sJcZi",
		"created_at": 1432937788,
		"user": {
			"id": "2874878782",
			"name": "boracho80"
		},
		"retweet_count": 0,
		"id": "604411007608459264",
		"favorite_count": 0
	},
	{
		"text": "Rocket Beans TV soll den Deutschen Webvideopreis gewinnen! https://t.co/JerY6Ebpuo #WVP15 @TheRocketBeans #rbtv",
		"created_at": 1432940209,
		"user": {
			"id": "93072709",
			"name": "BigPaddy89"
		},
		"retweet_count": 0,
		"id": "604421163721338880",
		"favorite_count": 1
	},
	{
		"text": "@TheRocketBeans RocketBeansTV wird als \"Besonderheit\" im aktuellen Twitch Artikel der c't Ausgabe 13 auf Seite 82 genannt! #rbtv #heise #ct",
		"created_at": 1432940938,
		"user": {
			"id": "2730027929",
			"name": "unewyear"
		},
		"retweet_count": 2,
		"id": "604424220093857792",
		"favorite_count": 2
	},
	{
		"text": "@daniele_rizzo w\u00fcrde gern was mit Euch machen, also hopp hopp ruft ihn an :D @budnoob @Bimon @EtienneToGo @DerHauge @boedefeld_ #rbtv",
		"created_at": 1432944901,
		"user": {
			"id": "3011968948",
			"name": "DenntoLP"
		},
		"retweet_count": 0,
		"id": "604440844263936000",
		"favorite_count": 0
	},
	{
		"text": "Und dann w\u00e4ren da noch die Moinmoins der letzten 3 Wochen zum gucken... und die Bohn Jours vom letzten Monat und und und... #rbtv",
		"created_at": 1432946389,
		"user": {
			"id": "172335258",
			"name": "EstrellaOscura"
		},
		"retweet_count": 0,
		"id": "604447082800390144",
		"favorite_count": 2
	},
	{
		"text": "Rocket Beans TV wird den Deutschen Webvideopreis gewinnen! #rbtv https://t.co/A62n19gli8 #WVP15",
		"created_at": 1432951023,
		"user": {
			"id": "2939754940",
			"name": "taikutsu910"
		},
		"retweet_count": 0,
		"id": "604466520182411264",
		"favorite_count": 3
	},
	{
		"text": "Ne stimmt, hast recht @budnoob - hab einfach vergessen den PC auszumachen ;) #rocketstats #rbtv",
		"created_at": 1432951473,
		"user": {
			"id": "61740184",
			"name": "Gronur"
		},
		"retweet_count": 0,
		"id": "604468407703089152",
		"favorite_count": 0
	},
	{
		"text": "@TheRocketBeans Falls Twitch keine Werbung sendet/f\u00fcr Nacht/Filler w\u00e4r btw d #Oculus Wartemusik super! #rbtv https://t.co/eiSYnI9GR0",
		"created_at": 1432954155,
		"user": {
			"id": "1558496984",
			"name": "derJOgelle"
		},
		"retweet_count": 1,
		"id": "604479655094153216",
		"favorite_count": 1
	},
	{
		"text": "Gerade das AlmostDaily-\u00c4ngste geschaut.Krass was so ein paar Worte ausrichten k\u00f6nnen.Danke @Bimon f\u00fcr deine tollen Abschluss Worte!\u2764\ufe0f #rbtv",
		"created_at": 1432960463,
		"user": {
			"id": "2258391633",
			"name": "LeonieChaoskind"
		},
		"retweet_count": 0,
		"id": "604506113535541248",
		"favorite_count": 6
	},
	{
		"text": "Ich will singen, und #rbtv gucken, und mein Bett will ich auch. Aber yay, Flughafen. http://t.co/opxx5T8qvM",
		"created_at": 1432972305,
		"user": {
			"id": "222783427",
			"name": "lomb4x"
		},
		"retweet_count": 0,
		"id": "604555782202531840",
		"favorite_count": 0
	},
	{
		"text": "Rocket Beans TV soll den Deutschen Webvideopreis gewinnen! https://t.co/Bl64eo0BdL #WVP15 #rbtv",
		"created_at": 1432973684,
		"user": {
			"id": "1017311174",
			"name": "TobiasSteffgen"
		},
		"retweet_count": 0,
		"id": "604561568597221378",
		"favorite_count": 1
	},
	{
		"text": "So ein toller Sendeplan und ich sitze bis um 20 Uhr in der Uni :( WIESO? #rbtv",
		"created_at": 1432973739,
		"user": {
			"id": "62791197",
			"name": "Alibabababy"
		},
		"retweet_count": 0,
		"id": "604561798939983874",
		"favorite_count": 0
	},
	{
		"text": "Don't hassel the Hoff! #Hasselhofff #KungFury #rbtv\n#kinoplus \n\nhttps://t.co/SWSFCTw81d",
		"created_at": 1432976219,
		"user": {
			"id": "2823725991",
			"name": "SarkasmusTV"
		},
		"retweet_count": 0,
		"id": "604572198100041728",
		"favorite_count": 1
	},
	{
		"text": "Wieviel #rbtv Bohnen stecken eigentlich #Insideps?\nund sind diese #Fairtrade? #moinmoin\nhttps://t.co/ruG1XHOB7s",
		"created_at": 1432976274,
		"user": {
			"id": "509869845",
			"name": "MarcelEdler"
		},
		"retweet_count": 0,
		"id": "604572430946959360",
		"favorite_count": 0
	},
	{
		"text": "Rocket Beans TV soll den Deutschen Webvideopreis gewinnen! GOGOGO!!!! https://t.co/6oWucZHIFB #WVP15 #rbtv",
		"created_at": 1432976829,
		"user": {
			"id": "77837734",
			"name": "OliChamploo"
		},
		"retweet_count": 0,
		"id": "604574759712620544",
		"favorite_count": 2
	},
	{
		"text": "Rocket Beans TV soll den Deutschen Webvideopreis gewinnen! https://t.co/xlNjeCFJDu #WVP15 #RBTV &lt;3",
		"created_at": 1432978410,
		"user": {
			"id": "1978297818",
			"name": "iggygustavo"
		},
		"retweet_count": 2,
		"id": "604581390500433920",
		"favorite_count": 1
	},
	{
		"text": "#Bug #Witcher3 Diesen Funny Bug habe ich gestern gefunden ;) #rbtv http://t.co/Q94R1H8F47",
		"created_at": 1432978772,
		"user": {
			"id": "757897458",
			"name": "Zihwih"
		},
		"retweet_count": 0,
		"id": "604582908406267906",
		"favorite_count": 0
	},
	{
		"text": "Um 12:30 starten wir heute locker-flockig mit einer Runde Mental of Honor und direkt danach Call of Budi #3! #rbtv http://t.co/jaGMaA6eoK",
		"created_at": 1432980080,
		"user": {
			"id": "370029585",
			"name": "TheRocketBeans"
		},
		"retweet_count": 2,
		"id": "604588394484756480",
		"favorite_count": 33
	},
	{
		"text": "Bloodborne | Knallhart Durchgenommen | #18 | 29.05.2015 | Part 1 | #rbtv http://t.co/aIsWtDy9SR",
		"created_at": 1432980114,
		"user": {
			"id": "370029585",
			"name": "TheRocketBeans"
		},
		"retweet_count": 1,
		"id": "604588536269029377",
		"favorite_count": 22
	},
	{
		"text": "mit @StufeTrashnight  @HookedMagazin  und dem anderen content wird #rbtv langsam zu einem richtigen Sender mit #gigagef\u00fchl @TheRocketBeans",
		"created_at": 1432980615,
		"user": {
			"id": "2932283589",
			"name": "RurBorusse"
		},
		"retweet_count": 1,
		"id": "604590639636967424",
		"favorite_count": 2
	},
	{
		"text": "Bloodborne | Knallhart Durchgenommen | #18 | 29.05.2015 | Part 2 | #rbtv http://t.co/mvXd6HMmDj",
		"created_at": 1432981900,
		"user": {
			"id": "370029585",
			"name": "TheRocketBeans"
		},
		"retweet_count": 1,
		"id": "604596027929296896",
		"favorite_count": 25
	},
	{
		"text": "#throwbacktweeterday '15-02-12: never forget, never forgive #rbtv\n\nhttps://t.co/whxZTs6taA",
		"created_at": 1432982522,
		"user": {
			"id": "2677770745",
			"name": "RolandTurambar"
		},
		"retweet_count": 0,
		"id": "604598635293241344",
		"favorite_count": 0
	},
	{
		"text": "#throwbacktweeterday '14-07-28: typisch @bimon #rbtv\n https://t.co/NZ920ykhfb",
		"created_at": 1432982659,
		"user": {
			"id": "2677770745",
			"name": "RolandTurambar"
		},
		"retweet_count": 0,
		"id": "604599209514438656",
		"favorite_count": 0
	},
	{
		"text": "eduard laser auf dem japan-tag?! das b\u00f6se kann wohl einpacken\n#rbtv #freiheit http://t.co/YJGodMh4HZ",
		"created_at": 1432983488,
		"user": {
			"id": "262340318",
			"name": "Lugetersch"
		},
		"retweet_count": 3,
		"id": "604602689293565953",
		"favorite_count": 59
	},
	{
		"text": "Hey @TheRocketBeans irre Idee f\u00fcr ein klasse Format:\nHost-spielt \"Der EINSAME Wolf\" mit der Community #rbtv http://t.co/OqwGp3XyX0",
		"created_at": 1432985963,
		"user": {
			"id": "2677770745",
			"name": "RolandTurambar"
		},
		"retweet_count": 0,
		"id": "604613069411635202",
		"favorite_count": 1
	},
	{
		"text": "@TheRocketBeans schon mies keinen grund zu nennen wieso kein Game+ l\u00e4uft...\n#drecksladen #rbtv",
		"created_at": 1432987540,
		"user": {
			"id": "2934140765",
			"name": "ohhiXD"
		},
		"retweet_count": 0,
		"id": "604619683044716544",
		"favorite_count": 0
	},
	{
		"text": "Also irgendwie finde ich ja, dass es wieder Zeit f\u00fcr ein neues #PenandPaper ist, oder? #rbtv",
		"created_at": 1432989284,
		"user": {
			"id": "58829408",
			"name": "T1mberwoulf"
		},
		"retweet_count": 0,
		"id": "604626999517319168",
		"favorite_count": 3
	},
	{
		"text": "Juhu! #rpc15 heute Abend auf #rbtv Ick froi mir!!",
		"created_at": 1432991012,
		"user": {
			"id": "194391911",
			"name": "Marco_W_S"
		},
		"retweet_count": 0,
		"id": "604634246817312768",
		"favorite_count": 0
	},
	{
		"text": "An diesem sch\u00f6nen Samstag hole ich jetzt ganz entspannt #CallOfBudi nach\n#rbtv #sc2",
		"created_at": 1432991633,
		"user": {
			"id": "279945117",
			"name": "jan0dal"
		},
		"retweet_count": 0,
		"id": "604636848787468288",
		"favorite_count": 1
	},
	{
		"text": "@LeSchroeck @EtienneToGo Wie w\u00e4re es mal mit einem Serien+ zum Kino+? #rbtv Mit gro\u00dfartigen Sachen wie #BlackSails #PennyDreadful #Banshee",
		"created_at": 1432991857,
		"user": {
			"id": "194391911",
			"name": "Marco_W_S"
		},
		"retweet_count": 1,
		"id": "604637789444042752",
		"favorite_count": 1
	},
	{
		"text": "Passend zur aktuellen #Bohnjour Folge von @TheRocketBeans @Siegismund #rbtv http://t.co/8sGlNLwg5r",
		"created_at": 1432994042,
		"user": {
			"id": "111846209",
			"name": "mjstriker"
		},
		"retweet_count": 1,
		"id": "604646955956977664",
		"favorite_count": 1
	},
	{
		"text": "Alter @StufeTrashnight folgt mir! Was geht?! #R\u00f6belTV #rbtv",
		"created_at": 1432994648,
		"user": {
			"id": "2154972272",
			"name": "BennoBreikopp"
		},
		"retweet_count": 1,
		"id": "604649495054413825",
		"favorite_count": 1
	},
	{
		"text": "okay #waskommenk\u00f6nnte schau ich noch, dann geh ich aber Einkaufen... #diefederistm\u00e4chtigeralsdasessen oder so... #rbtv",
		"created_at": 1432995367,
		"user": {
			"id": "2677770745",
			"name": "RolandTurambar"
		},
		"retweet_count": 0,
		"id": "604652512461897728",
		"favorite_count": 0
	},
	{
		"text": "Wenn Witze Backfiren! @artsykatsy Von wegen Photoshop Approved ;) Der @Colin_Gaebel bleibt verschont! #rbtv #bohnjour http://t.co/cB0F0iZKoo",
		"created_at": 1432995456,
		"user": {
			"id": "568187666",
			"name": "rinkusart"
		},
		"retweet_count": 0,
		"id": "604652886501519360",
		"favorite_count": 2
	},
	{
		"text": "@TheRocketBeans @boedefeld_ @Bimon Nils' Gedeankliche Absurdit\u00e4t als Theorie https://t.co/xvKsmB1hXG  #rbtv #waskommenk\u00f6nnte",
		"created_at": 1432995848,
		"user": {
			"id": "884963762",
			"name": "Maxlampi"
		},
		"retweet_count": 0,
		"id": "604654531650199553",
		"favorite_count": 0
	},
	{
		"text": "Junge Junge, der Wochenplan f\u00fcr n\u00e4chste Woche liest sich ja echt wie 1! Viel Live &amp; viele Premieren: #l\u00e4uftbeieuch @TheRocketBeans #rbtv",
		"created_at": 1432999820,
		"user": {
			"id": "1430839081",
			"name": "wasauchimmmer"
		},
		"retweet_count": 0,
		"id": "604671190880423936",
		"favorite_count": 0
	},
	{
		"text": "#hutcurup #rbtv #camkoha #photogrid @faydroumz https://t.co/RSCa9d5upR",
		"created_at": 1433001299,
		"user": {
			"id": "361680456",
			"name": "seno_wijaya"
		},
		"retweet_count": 0,
		"id": "604677392959946753",
		"favorite_count": 0
	},
	{
		"text": "\u00d6h, Bild in Zeitlupe, Ton normale Geschwindigkeit. Sonst noch wer? #rbtv",
		"created_at": 1433001386,
		"user": {
			"id": "51030748",
			"name": "NerdZoneBlog"
		},
		"retweet_count": 0,
		"id": "604677759797895168",
		"favorite_count": 2
	},
	{
		"text": "Minecraft | Zocken mit Bohnen | #9 | 28.05.2015 | #rbtv http://t.co/agQ4AR5u6V",
		"created_at": 1433001892,
		"user": {
			"id": "370029585",
			"name": "TheRocketBeans"
		},
		"retweet_count": 1,
		"id": "604679882010935296",
		"favorite_count": 20
	},
	{
		"text": "Jetzt geht wohl gar nix mehr bei #rbtv hatte mich ja auf #Couchkolumne und #Diced gefreut :(",
		"created_at": 1433002031,
		"user": {
			"id": "51030748",
			"name": "NerdZoneBlog"
		},
		"retweet_count": 0,
		"id": "604680464784367617",
		"favorite_count": 0
	},
	{
		"text": "@TheRocketBeans ich glaube ihr solltet euch mal um dem Stream kummern seid 5min gibt es ein Standbild. #rbtv",
		"created_at": 1433002035,
		"user": {
			"id": "760204566",
			"name": "Demoria93"
		},
		"retweet_count": 0,
		"id": "604680480609452032",
		"favorite_count": 0
	},
	{
		"text": "Alles klar #rbtv. Ich gehe jetzt weiterlernen. \ud83d\ude2b\ud83d\ude2d.",
		"created_at": 1433002109,
		"user": {
			"id": "353923586",
			"name": "TomulErnst"
		},
		"retweet_count": 0,
		"id": "604680790174273536",
		"favorite_count": 0
	},
	{
		"text": "Jemand zu hause @TheRocketBeans ? \u2665\n#rbtv",
		"created_at": 1433002151,
		"user": {
			"id": "110128109",
			"name": "ultrakult"
		},
		"retweet_count": 0,
		"id": "604680965579927554",
		"favorite_count": 0
	},
	{
		"text": "Lag is back? Macht nix, ich liebe #rbtv auch als Standbild! &lt;3 @TheRocketBeans",
		"created_at": 1433002341,
		"user": {
			"id": "2986052902",
			"name": "lilalauneschaf"
		},
		"retweet_count": 0,
		"id": "604681764225716224",
		"favorite_count": 1
	},
	{
		"text": "Standbild ... #rbtv",
		"created_at": 1433002353,
		"user": {
			"id": "21393627",
			"name": "ping_u"
		},
		"retweet_count": 0,
		"id": "604681812703608832",
		"favorite_count": 0
	},
	{
		"text": "@TheRocketBeans #rbtv ich glaube ich bin nicht de erste der das schreibt, aber eurer Stream h\u00e4ngt #servicetweet",
		"created_at": 1433002362,
		"user": {
			"id": "150823730",
			"name": "Thy21"
		},
		"retweet_count": 0,
		"id": "604681852276887556",
		"favorite_count": 0
	},
	{
		"text": "#RBTV at its best!\n#allesmussnixkann\n#standbild\n@TheRocketBeans http://t.co/JPacs15C13",
		"created_at": 1433002380,
		"user": {
			"id": "221534796",
			"name": "AnkheeTheMonkee"
		},
		"retweet_count": 1,
		"id": "604681928739028992",
		"favorite_count": 2
	},
	{
		"text": "#rbtv -Stream kaputt!!!1!!elf SwiftRage ^^ @TheRocketBeans",
		"created_at": 1433002457,
		"user": {
			"id": "2826019323",
			"name": "_Rick_Rocks_"
		},
		"retweet_count": 0,
		"id": "604682248110153728",
		"favorite_count": 0
	},
	{
		"text": "zzzzZZZZ #rbtv http://t.co/uU7o0MIqSy",
		"created_at": 1433002542,
		"user": {
			"id": "3153418288",
			"name": "DenzeI1982"
		},
		"retweet_count": 0,
		"id": "604682607360622594",
		"favorite_count": 0
	},
	{
		"text": "Minecraft | Zocken mit Bohnen | #10 | 28.05.2015 | #rbtv http://t.co/iHC5tscK1X",
		"created_at": 1433003464,
		"user": {
			"id": "370029585",
			"name": "TheRocketBeans"
		},
		"retweet_count": 1,
		"id": "604686474529910784",
		"favorite_count": 21
	},
	{
		"text": "Ihr habts wieder geschafft #rbtv @TheRocketBeans #witzefrei #neomagazinroyal",
		"created_at": 1433004164,
		"user": {
			"id": "514626623",
			"name": "xsuchtiTV"
		},
		"retweet_count": 0,
		"id": "604689410123264000",
		"favorite_count": 0
	},
	{
		"text": "#rbtv BEEF &gt; #DFBPokal  - Hat einfach mehr Skill! https://t.co/ccAWYToCSm",
		"created_at": 1433004354,
		"user": {
			"id": "194391911",
			"name": "Marco_W_S"
		},
		"retweet_count": 0,
		"id": "604690207565152256",
		"favorite_count": 0
	},
	{
		"text": "Da ist wohl jemand \u00fcbers Internetkabel gestolpert! @therocketbeans #rbtv #offline :D",
		"created_at": 1433004357,
		"user": {
			"id": "2930603231",
			"name": "AlphaZen_"
		},
		"retweet_count": 0,
		"id": "604690219032563712",
		"favorite_count": 0
	},
	{
		"text": "#rbtv -Stream ist tot ! :'( @TheRocketBeans",
		"created_at": 1433004598,
		"user": {
			"id": "2826019323",
			"name": "_Rick_Rocks_"
		},
		"retweet_count": 0,
		"id": "604691228106596352",
		"favorite_count": 0
	},
	{
		"text": "Minecraft | Zocken mit Bohnen | #11 | 28.05.2015 | #rbtv http://t.co/7eIIUxUMWo",
		"created_at": 1433005282,
		"user": {
			"id": "370029585",
			"name": "TheRocketBeans"
		},
		"retweet_count": 0,
		"id": "604694099095113728",
		"favorite_count": 21
	},
	{
		"text": "Katharina\u2019s letzter Blogeintrag macht mich traurig. :( #rbtv",
		"created_at": 1433005491,
		"user": {
			"id": "106542587",
			"name": "upandawayXO"
		},
		"retweet_count": 0,
		"id": "604694974999982080",
		"favorite_count": 0
	},
	{
		"text": "@maexdaemaege Klar soweit? http://t.co/u57AgZS4d5 #rbtv #dadadadada",
		"created_at": 1433005524,
		"user": {
			"id": "610217842",
			"name": "bastistuta_"
		},
		"retweet_count": 0,
		"id": "604695115622457344",
		"favorite_count": 1
	},
	{
		"text": "Ich freu mich schon auf den Reisebericht \u00fcber die RPC von @BelliBell und @Lugetersch #rbtv",
		"created_at": 1433007080,
		"user": {
			"id": "2888388287",
			"name": "Ansuil_"
		},
		"retweet_count": 1,
		"id": "604701641946865665",
		"favorite_count": 1
	},
	{
		"text": "Minecraft | Zocken mit Bohnen | #12 | 28.05.2015 | #rbtv http://t.co/G6mxwqTjYo",
		"created_at": 1433007272,
		"user": {
			"id": "370029585",
			"name": "TheRocketBeans"
		},
		"retweet_count": 0,
		"id": "604702446707978240",
		"favorite_count": 23
	},
	{
		"text": "Na dann gucken wir do h mal, was @Lugetersch und @BelliBell so von der RPC berichten :-) #rbtv",
		"created_at": 1433007409,
		"user": {
			"id": "273006013",
			"name": "mekashifu"
		},
		"retweet_count": 0,
		"id": "604703019058515969",
		"favorite_count": 0
	},
	{
		"text": "Mal gucken, wie viele moinmoins ich heute noch schaffe... #rbtv",
		"created_at": 1433007961,
		"user": {
			"id": "172335258",
			"name": "EstrellaOscura"
		},
		"retweet_count": 0,
		"id": "604705333672603649",
		"favorite_count": 1
	},
	{
		"text": "@malteniccals @TheRocketBeans #game+ f\u00e4llt aus weil Mastermind Micha im Urlaub ist und #rbtv aktuelle eine gro\u00dfe Reise planen muss",
		"created_at": 1433008568,
		"user": {
			"id": "1244892288",
			"name": "RayConner_de"
		},
		"retweet_count": 1,
		"id": "604707880248479744",
		"favorite_count": 1
	},
	{
		"text": "gleich almost daily #rbtv http://t.co/pj9jKCEp7M",
		"created_at": 1433009654,
		"user": {
			"id": "95047373",
			"name": "T1gerpanzer"
		},
		"retweet_count": 0,
		"id": "604712434822205441",
		"favorite_count": 0
	},
	{
		"text": "Der Reisebericht von @BelliBell war gro\u00dfartig. Und mein Neid wegen Hodor steht mir ins Gesicht geschrieben #rbtv",
		"created_at": 1433009907,
		"user": {
			"id": "1722386514",
			"name": "Obiturady"
		},
		"retweet_count": 1,
		"id": "604713499323969537",
		"favorite_count": 0
	},
	{
		"text": "Geniales Thema heute bei #AlmostDaily :D Staubf\u00e4nger. Oh ich hab 'ne Schw\u00e4che f\u00fcr Staubf\u00e4nger! &lt;3 #rbtv",
		"created_at": 1433010110,
		"user": {
			"id": "2258391633",
			"name": "LeonieChaoskind"
		},
		"retweet_count": 0,
		"id": "604714350880899072",
		"favorite_count": 5
	},
	{
		"text": "Ich dachte ja erst, \"Staubf\u00e4nger? Hm... neee\". Aber jetzt habt ihr mich. :D @therocketbeans #almostdaily #rbtv @bimon @budnoob @colin_gaebel",
		"created_at": 1433010597,
		"user": {
			"id": "2930603231",
			"name": "AlphaZen_"
		},
		"retweet_count": 0,
		"id": "604716392580038656",
		"favorite_count": 1
	},
	{
		"text": "\"W\u00e4sche ist mein Staubbeutel.\"  Hach,  Simon. #rbtv #almostdaily",
		"created_at": 1433010621,
		"user": {
			"id": "1184005195",
			"name": "SherbetSlinger"
		},
		"retweet_count": 0,
		"id": "604716491905343488",
		"favorite_count": 0
	},
	{
		"text": "Den Hund mit Pfeil Richtung Penis hat SImon schon \u00f6fters erw\u00e4hnt. Ich erinnere mich da an einige Plauschangriffe :D #rbtv #AlmostDaily",
		"created_at": 1433010622,
		"user": {
			"id": "463748542",
			"name": "Moon_N7"
		},
		"retweet_count": 0,
		"id": "604716496720412673",
		"favorite_count": 0
	},
	{
		"text": "Steine hab ich auch zuhaus rumliegen. Alle aus irgendeinem Urlaub xD #rbtv #almostdaily",
		"created_at": 1433011026,
		"user": {
			"id": "266569727",
			"name": "MsDuststorm"
		},
		"retweet_count": 0,
		"id": "604718192083275776",
		"favorite_count": 0
	},
	{
		"text": "Heute: Simon und die Messis. #rbtv #almostdaily",
		"created_at": 1433011673,
		"user": {
			"id": "84288314",
			"name": "_AleX_Page_"
		},
		"retweet_count": 0,
		"id": "604720903046475776",
		"favorite_count": 0
	},
	{
		"text": "@Colin_Gaebel du willst doch immer feedback von uns... da haste :D &lt;3 #rbtv http://t.co/HgsZZGVZjx",
		"created_at": 1433011864,
		"user": {
			"id": "2338667575",
			"name": "Gisi1800"
		},
		"retweet_count": 0,
		"id": "604721707639828481",
		"favorite_count": 3
	},
	{
		"text": "Liebe #rbtv Fans Mein Freund @PolygonoFactor &amp;ich suchen ein paar Leute f\u00fcr einen Podcast \u00fcber die @TheRocketBeans bzw \u00fcber Giga&amp;G1",
		"created_at": 1433012006,
		"user": {
			"id": "284747622",
			"name": "Buffynator"
		},
		"retweet_count": 0,
		"id": "604722301104451584",
		"favorite_count": 1
	},
	{
		"text": "Krass dass Ingo Mess das Spiel pfeift. #BVB #BVBWOB #Pokalfinale #rbtv @TheRocketBeans",
		"created_at": 1433013697,
		"user": {
			"id": "819843248",
			"name": "DieAcademy"
		},
		"retweet_count": 0,
		"id": "604729395975204864",
		"favorite_count": 0
	},
	{
		"text": "Hey @janboehm ! Wenn dir in der Sommerpause langweilig wird, sei doch mal Gast bei #bohnjour auf #rbtv mit den Jungs von @TheRocketBeans",
		"created_at": 1433016300,
		"user": {
			"id": "3022409764",
			"name": "Zaddik23"
		},
		"retweet_count": 0,
		"id": "604740311831707648",
		"favorite_count": 1
	},
	{
		"text": "Half-Life: Blue Shift | Zocken mit Bohnen | #1 | 28.05.2015 | #rbtv http://t.co/0QTIllDkyK",
		"created_at": 1433016325,
		"user": {
			"id": "370029585",
			"name": "TheRocketBeans"
		},
		"retweet_count": 0,
		"id": "604740418501275648",
		"favorite_count": 29
	},
	{
		"text": "\"Angriffskrieg?\"\n\"Nein. Wir fragen milit\u00e4risch nach ob wir das Land haben k\u00f6nnen\" \nGro\u00dfartig #RBTV",
		"created_at": 1433017115,
		"user": {
			"id": "591325099",
			"name": "DevilsToast"
		},
		"retweet_count": 1,
		"id": "604743730487279617",
		"favorite_count": 2
	},
	{
		"text": "@EtienneToGo @TheRocketBeans #rbtv k\u00f6nnen wir BITTE ein #kinoplus zu #KungFury haben",
		"created_at": 1433017765,
		"user": {
			"id": "1280099564",
			"name": "Mad_OHara"
		},
		"retweet_count": 0,
		"id": "604746456872927232",
		"favorite_count": 0
	},
	{
		"text": "BESTE!! NACHTSCHICHT!! EVER!!! @TheRocketBeans @boedefeld_ #rbtv #allesoriginal #tears2hype http://t.co/2CFMlUc1X0",
		"created_at": 1433017770,
		"user": {
			"id": "1513608566",
			"name": "murdoc1896"
		},
		"retweet_count": 0,
		"id": "604746478419120128",
		"favorite_count": 0
	},
	{
		"text": "Half-Life: Blue Shift | Zocken mit Bohnen | #2 | 28.05.2015 | #rbtv http://t.co/VWaDEnL3oy",
		"created_at": 1433017932,
		"user": {
			"id": "370029585",
			"name": "TheRocketBeans"
		},
		"retweet_count": 0,
		"id": "604747158651314176",
		"favorite_count": 25
	},
	{
		"text": "Rocket Beans TV soll den Deutschen Webvideopreis gewinnen! https://t.co/51Jcm14VwN #WVP15 #RBTV",
		"created_at": 1433017961,
		"user": {
			"id": "1708118120",
			"name": "Dirgni_onherway"
		},
		"retweet_count": 0,
		"id": "604747279501795328",
		"favorite_count": 1
	},
	{
		"text": "Jetzt 2,5 Stunden die H\u00fcbschen auf #rbtv\nAbend ist gerettet! http://t.co/Lnj7uzy7ZP",
		"created_at": 1433018302,
		"user": {
			"id": "237317029",
			"name": "Meuchelhorst"
		},
		"retweet_count": 0,
		"id": "604748707653906432",
		"favorite_count": 0
	},
	{
		"text": "@EtienneToGo Wie hei\u00dft \"Arschkalt\"auf S\u00e4chsisch? \"BoFrost\" #standup #rbtv",
		"created_at": 1433018345,
		"user": {
			"id": "284747622",
			"name": "Buffynator"
		},
		"retweet_count": 0,
		"id": "604748889279864832",
		"favorite_count": 0
	},
	{
		"text": "Jealousy\nTurning saints into the sea\nTurning through sick lullabies\nChoking on your alibis\nBut it's just the price I pay \ud83c\udfb6 #dosenbeatz #rbtv",
		"created_at": 1433019135,
		"user": {
			"id": "797904992",
			"name": "Liliweh"
		},
		"retweet_count": 1,
		"id": "604752204172537856",
		"favorite_count": 5
	},
	{
		"text": "Dieses Lied steckt voller Erinnerungen. \ud83d\udc99 #rbtv",
		"created_at": 1433019237,
		"user": {
			"id": "797904992",
			"name": "Liliweh"
		},
		"retweet_count": 0,
		"id": "604752631752474624",
		"favorite_count": 1
	},
	{
		"text": "@Creeveey das lief gerade auf #rbtv. \ud83d\ude0a",
		"created_at": 1433019349,
		"user": {
			"id": "797904992",
			"name": "Liliweh"
		},
		"retweet_count": 0,
		"id": "604753099618693120",
		"favorite_count": 1
	},
	{
		"text": "Samstag Abend. Bohn Jour Musik und ein Malbuch. Ist das dieses \"erwachsen sein\", wovon alle immer reden? #rbtv http://t.co/d3cxFRzjfd",
		"created_at": 1433019430,
		"user": {
			"id": "106542587",
			"name": "upandawayXO"
		},
		"retweet_count": 0,
		"id": "604753441089536000",
		"favorite_count": 3
	},
	{
		"text": "wieder geile Mucke bei #rbtv #dosenbeatz !!!! :-)",
		"created_at": 1433019555,
		"user": {
			"id": "121535855",
			"name": "deaftoned"
		},
		"retweet_count": 0,
		"id": "604753962126962688",
		"favorite_count": 1
	},
	{
		"text": "Half-Life: Blue Shift | Zocken mit Bohnen | #3 | 28.05.2015 | #rbtv http://t.co/QxbN6jE6Tx",
		"created_at": 1433019659,
		"user": {
			"id": "370029585",
			"name": "TheRocketBeans"
		},
		"retweet_count": 0,
		"id": "604754399022460928",
		"favorite_count": 29
	},
	{
		"text": "@TheRocketBeans schon irgendwie geil, wie #rbtv 3 Folgen Half Life Opposing Force als \"Blue Shift\" hochl\u00e4dt, sogar mit falschem Teaserbild.",
		"created_at": 1433019875,
		"user": {
			"id": "2730027929",
			"name": "unewyear"
		},
		"retweet_count": 0,
		"id": "604755304270733314",
		"favorite_count": 0
	},
	{
		"text": "Selbst @pewdiepie  nennt sein Pferd in Witcher 3 schon Gunnar @Gunnsen :D #Witcher3  #pewdiepie #rbtv #gunnar  #64k #moinmoin",
		"created_at": 1433019942,
		"user": {
			"id": "2990583813",
			"name": "HappyHuy94"
		},
		"retweet_count": 0,
		"id": "604755588971675649",
		"favorite_count": 2
	},
	{
		"text": "@boedefeld_ sag deinen Jungs und M\u00e4dels bei #rbtv ruhig mal, dass Sie bei YT gerade dein \"Opposing Force\" als \"Blue Shift\" hochladen :-)",
		"created_at": 1433020888,
		"user": {
			"id": "2730027929",
			"name": "unewyear"
		},
		"retweet_count": 0,
		"id": "604759554736463872",
		"favorite_count": 0
	},
	{
		"text": "@TheRocketBeans #dosenbeatz #rbtv #moinmoin http://t.co/7XDtZAZ4Wo",
		"created_at": 1433021318,
		"user": {
			"id": "3044532255",
			"name": "eXtreMe2k14"
		},
		"retweet_count": 0,
		"id": "604761358433927168",
		"favorite_count": 0
	},
	{
		"text": "#rbtv am Ghost Busters Automat im Wynn #rocketbeans #lasvegas #telebeans #wynn #ghostbusters https://t.co/7glMXAEPZL",
		"created_at": 1433022307,
		"user": {
			"id": "1506678566",
			"name": "DZMediaGer"
		},
		"retweet_count": 0,
		"id": "604765506676109313",
		"favorite_count": 0
	},
	{
		"text": "#stanlee #hulk #rbtv #rocketbeans #shutupandtakemymoney !!!! https://t.co/J8RsJYeFER",
		"created_at": 1433022337,
		"user": {
			"id": "1506678566",
			"name": "DZMediaGer"
		},
		"retweet_count": 0,
		"id": "604765632354222081",
		"favorite_count": 0
	}
]