[
	{
		"text": "Speziell @EtienneToGo k\u00f6nnte dieser Fanfilm besonders gut gefallen: https://t.co/h2aWpqXWhk #Metroid #rbtv #Samus",
		"created_at": 1446505584,
		"user": {
			"id": "339088850",
			"name": "Dan_Morgenstern"
		},
		"retweet_count": 0,
		"id": "661318470425014272",
		"favorite_count": 0
	},
	{
		"text": "Ich muss schon sagen; das ging schnell  #rbtv https://t.co/Qk11ywRH2b",
		"created_at": 1446505712,
		"user": {
			"id": "2981501169",
			"name": "Philicore"
		},
		"retweet_count": 0,
		"id": "661319006876475395",
		"favorite_count": 0
	},
	{
		"text": "#moinmoin #rbtv \nDas ist mein tattoo das wird noch weiter gestochen  das wird biomechanic Realit\u00e4t\nDaniel Boddenberg https://t.co/4DCjnepw35",
		"created_at": 1446506386,
		"user": {
			"id": "1702822171",
			"name": "DerSmurff"
		},
		"retweet_count": 0,
		"id": "661321834525286401",
		"favorite_count": 0
	},
	{
		"text": "#HartzV wartet dem Hund #rbtv https://t.co/43wK5QZwJp",
		"created_at": 1446510626,
		"user": {
			"id": "4025619808",
			"name": "ForceOneBot"
		},
		"retweet_count": 0,
		"id": "661339615605952513",
		"favorite_count": 0
	},
	{
		"text": "Guten morgen liebe B\u00f6hnchen! Entspannten Tag allen! #moinmoin #rbtv #rocketbeans #gutenmorgen #moin @TheRocketBeans https://t.co/4RTxBwfFma",
		"created_at": 1446531409,
		"user": {
			"id": "2396773361",
			"name": "ColinMoriaty"
		},
		"retweet_count": 0,
		"id": "661426789156302848",
		"favorite_count": 0
	},
	{
		"text": "@TheRocketBeans @Bimon @boedefeld_ nehmt ihr Empfehlungen f\u00fcr den Buchklub? #rbtv",
		"created_at": 1446532979,
		"user": {
			"id": "57908894",
			"name": "fabiotherealone"
		},
		"retweet_count": 0,
		"id": "661433370786848768",
		"favorite_count": 0
	},
	{
		"text": "@MrCrackerMicha Guten Morgen. Schon jemand im Sender? Bitte mal den Sound checken. Es stottert tierisch.. Danke im voraus :) #rbtv",
		"created_at": 1446537968,
		"user": {
			"id": "3079013866",
			"name": "Raketenbaer"
		},
		"retweet_count": 0,
		"id": "661454298505695232",
		"favorite_count": 0
	},
	{
		"text": "@mopo Ein Fall f\u00fcr Inspektor @boedefeld_?! #rbtv #moinmoin",
		"created_at": 1446537977,
		"user": {
			"id": "97406649",
			"name": "Stuessy79"
		},
		"retweet_count": 0,
		"id": "661454335939883008",
		"favorite_count": 0
	},
	{
		"text": "Heute fr\u00fcher, da ich gleich unterwegs bin! Euer Sendeplan~ \u2665 #rbtv #sendeplan https://t.co/p8sYVEVrEs",
		"created_at": 1446538180,
		"user": {
			"id": "2347700878",
			"name": "Lyannachan"
		},
		"retweet_count": 0,
		"id": "661455187102539776",
		"favorite_count": 6
	},
	{
		"text": "Homeoffice at it's best!\nStatt Radio: \"Erwachsene M\u00e4nner h\u00f6ren Jan Tenner.\" #rbtv #RocketBeansTV #jantenner",
		"created_at": 1446539827,
		"user": {
			"id": "64676605",
			"name": "tricky_r"
		},
		"retweet_count": 0,
		"id": "661462097025454080",
		"favorite_count": 0
	},
	{
		"text": "ich hab Kontakt zu Aliens #moinmoin #rbtv",
		"created_at": 1446543167,
		"user": {
			"id": "358310191",
			"name": "shabracke"
		},
		"retweet_count": 0,
		"id": "661476102574112768",
		"favorite_count": 1
	},
	{
		"text": "Rettet den Sound! #moinmoin #rbtv",
		"created_at": 1446543179,
		"user": {
			"id": "3014922071",
			"name": "Kronbaer"
		},
		"retweet_count": 0,
		"id": "661476154314989568",
		"favorite_count": 0
	},
	{
		"text": "@TheRocketBeans was is denn da los ? das bild und er ton sind ein einziges geruckel #rbtv",
		"created_at": 1446543219,
		"user": {
			"id": "166899533",
			"name": "Rattleraptor82"
		},
		"retweet_count": 0,
		"id": "661476323521531905",
		"favorite_count": 0
	},
	{
		"text": "Ich glaub @TheRocketBeans haben Twitch durchgespielt und jetzt ist es kaputt. #rbtv #moinmoin",
		"created_at": 1446543226,
		"user": {
			"id": "2563816790",
			"name": "FrauNasenbaer"
		},
		"retweet_count": 0,
		"id": "661476351837388800",
		"favorite_count": 1
	},
	{
		"text": "#rbtv Hey ihr habt extreme Sender Probleme der Ton h\u00f6rt sich an als wird er durch den Mixer gejagt",
		"created_at": 1446543260,
		"user": {
			"id": "1702822171",
			"name": "DerSmurff"
		},
		"retweet_count": 0,
		"id": "661476493466468352",
		"favorite_count": 0
	},
	{
		"text": "#rbtv  Eh, bin zu faul ein ganz eigenen Anfangs-Post zu machen, weswegen ich meinen alten aus dem Pirateboard\u2026 https://t.co/v6xXxChWQN",
		"created_at": 1446543305,
		"user": {
			"id": "3017523491",
			"name": "rbtvcommunity"
		},
		"retweet_count": 0,
		"id": "661476681476145152",
		"favorite_count": 0
	},
	{
		"text": "Oder @TheRocketBeans haben endlich Kontakt zu Aliens aufgenommen :D #rbtv #moinmoin",
		"created_at": 1446543340,
		"user": {
			"id": "2563816790",
			"name": "FrauNasenbaer"
		},
		"retweet_count": 0,
		"id": "661476828838662144",
		"favorite_count": 1
	},
	{
		"text": "Entweder habe ich einen Gremlin im Fernseher, oder das sind Vorzeichen einer Inversion von Aliens! :D  #moinmoin #rbtv",
		"created_at": 1446543474,
		"user": {
			"id": "1588997233",
			"name": "ITamyI"
		},
		"retweet_count": 0,
		"id": "661477393241088000",
		"favorite_count": 0
	},
	{
		"text": "Twich geht wieder Check ! Bereit auf Moin Moin Check dann kanns losgehen #rbtv #moinmoin",
		"created_at": 1446543486,
		"user": {
			"id": "2981523053",
			"name": "K3nJi87"
		},
		"retweet_count": 0,
		"id": "661477441580462080",
		"favorite_count": 0
	},
	{
		"text": "L\u00e4uft ja noch gar nicht?! Puh! Ich dachte schon, dass ich den Anfang von #moinmoin verpasst h\u00e4tte. #rbtv",
		"created_at": 1446543488,
		"user": {
			"id": "97406649",
			"name": "Stuessy79"
		},
		"retweet_count": 0,
		"id": "661477450615037952",
		"favorite_count": 0
	},
	{
		"text": "@TheRocketBeans Geil neues Studio \ud83d\ude0e Hoffentlich bleibt das #moinmoin #rbtv",
		"created_at": 1446543563,
		"user": {
			"id": "774073250",
			"name": "takenoyujin"
		},
		"retweet_count": 0,
		"id": "661477766085373952",
		"favorite_count": 0
	},
	{
		"text": "#rbtv #moinmoin #geili\nIch liebe moinmoin mit gregor am morgen https://t.co/UD7sQCan5s",
		"created_at": 1446543609,
		"user": {
			"id": "1014041096",
			"name": "MartinaF5"
		},
		"retweet_count": 0,
		"id": "661477956645208064",
		"favorite_count": 0
	},
	{
		"text": "Der Hashtag ist total super :D #rbtv #moinmoin #geili",
		"created_at": 1446543609,
		"user": {
			"id": "2563816790",
			"name": "FrauNasenbaer"
		},
		"retweet_count": 0,
		"id": "661477956477407232",
		"favorite_count": 0
	},
	{
		"text": "Fr\u00fc\u00fc\u00fc\u00fchst\u00fcck!! #moinmoin #rbtv ist so #geili https://t.co/oUegdz23yk",
		"created_at": 1446543612,
		"user": {
			"id": "797904992",
			"name": "Liliweh"
		},
		"retweet_count": 0,
		"id": "661477969278451712",
		"favorite_count": 3
	},
	{
		"text": "#geili #rbtv #moinmoin Guten morgen Gregor! &lt;3",
		"created_at": 1446543620,
		"user": {
			"id": "961272043",
			"name": "suuN91togo"
		},
		"retweet_count": 0,
		"id": "661478003743002624",
		"favorite_count": 0
	},
	{
		"text": "#RBTV #MOINMOIN #geili WTF, bester # und ich mit Chips zum Fr\u00fchst\u00fcck, nach 2 Stunden Physik",
		"created_at": 1446543631,
		"user": {
			"id": "319549036",
			"name": "nurdermarcus"
		},
		"retweet_count": 0,
		"id": "661478049091858432",
		"favorite_count": 0
	},
	{
		"text": "Na, super. @Chaz_Ashley geht auf Hashtag-Safari. \ud83d\ude09 #geili #moinmoin #rbtv",
		"created_at": 1446543639,
		"user": {
			"id": "3014922071",
			"name": "Kronbaer"
		},
		"retweet_count": 0,
		"id": "661478082423844864",
		"favorite_count": 0
	},
	{
		"text": "#moinmoin #rbtv #geili Geburtstag, ausgeschlafen und moinmoin mit Gregott &lt;3",
		"created_at": 1446543650,
		"user": {
			"id": "60110008",
			"name": "Jinison"
		},
		"retweet_count": 0,
		"id": "661478128569720833",
		"favorite_count": 1
	},
	{
		"text": "Gregor du machst aus ein schlechten Hashtag ein Kult Hashtag ! #rbtv #moin #geili",
		"created_at": 1446543657,
		"user": {
			"id": "2981523053",
			"name": "K3nJi87"
		},
		"retweet_count": 0,
		"id": "661478160551268352",
		"favorite_count": 0
	},
	{
		"text": "\"Es geht weiter, yaks, gleichheitszeichen\" Sehr sch\u00f6n :D #geili #moinmoin #rbtv",
		"created_at": 1446543659,
		"user": {
			"id": "2563816790",
			"name": "FrauNasenbaer"
		},
		"retweet_count": 0,
		"id": "661478167115227136",
		"favorite_count": 0
	},
	{
		"text": "Bin ich jetzt im fernsehn?\n\n#rbtv #moinmoin #geili",
		"created_at": 1446543672,
		"user": {
			"id": "3365575881",
			"name": "derkonrad511"
		},
		"retweet_count": 0,
		"id": "661478221918175232",
		"favorite_count": 0
	},
	{
		"text": "#rbtv #moinmoin Morg\u00e4n https://t.co/jFr1y5nPJN",
		"created_at": 1446543673,
		"user": {
			"id": "921651420",
			"name": "Esusa90"
		},
		"retweet_count": 0,
		"id": "661478227144232960",
		"favorite_count": 0
	},
	{
		"text": "MoinMoin mit Gregott in der Schule *Kreygasm* #rbtv #MoinMoin #geili https://t.co/EjIXUDDrqg",
		"created_at": 1446543681,
		"user": {
			"id": "1405585802",
			"name": "Raiden_956"
		},
		"retweet_count": 0,
		"id": "661478261441077249",
		"favorite_count": 0
	},
	{
		"text": "#geili beschreibt GreGeil sehr gut! #moinmoin #rbtv",
		"created_at": 1446543682,
		"user": {
			"id": "3357096137",
			"name": "GiraffenGuru"
		},
		"retweet_count": 0,
		"id": "661478265719267328",
		"favorite_count": 0
	},
	{
		"text": "#rbtv #moinmoin #geili https://t.co/Akc6gr1drY",
		"created_at": 1446543683,
		"user": {
			"id": "57908894",
			"name": "fabiotherealone"
		},
		"retweet_count": 1,
		"id": "661478269531893760",
		"favorite_count": 2
	},
	{
		"text": "Gregor schaut aus wie Cesaro \ud83d\ude01  #moinmoin #RBTV #geili",
		"created_at": 1446543698,
		"user": {
			"id": "774073250",
			"name": "takenoyujin"
		},
		"retweet_count": 0,
		"id": "661478329808195584",
		"favorite_count": 0
	},
	{
		"text": "#geili #geili Supertyp. Warum hat dich keiner lieb? #rbtv #moinmoin",
		"created_at": 1446543720,
		"user": {
			"id": "431087779",
			"name": "OffTheBreakProd"
		},
		"retweet_count": 0,
		"id": "661478422644981760",
		"favorite_count": 0
	},
	{
		"text": "moin Gregor, das ist eine super Idee =D\n#rbtv #geili #moinmoin",
		"created_at": 1446543721,
		"user": {
			"id": "3390654135",
			"name": "HerrGeilen"
		},
		"retweet_count": 0,
		"id": "661478429242601472",
		"favorite_count": 0
	},
	{
		"text": "Ich werd immer total #geili wenn #moinmoin kommt. #rbtv",
		"created_at": 1446543728,
		"user": {
			"id": "56374732",
			"name": "kaltric"
		},
		"retweet_count": 0,
		"id": "661478455461171200",
		"favorite_count": 0
	},
	{
		"text": "Lets go #rbtv #geili #moinmoin https://t.co/1u7myAQLNk",
		"created_at": 1446543730,
		"user": {
			"id": "840488010",
			"name": "Mecci_official"
		},
		"retweet_count": 0,
		"id": "661478466328657920",
		"favorite_count": 0
	},
	{
		"text": "moin Moin gregsen die Ton Probleme sind behoben super danke das fing schon seit fast 3 Stunden so lieben Gru\u00df Daniel #rbtv #moinmoin",
		"created_at": 1446543737,
		"user": {
			"id": "1702822171",
			"name": "DerSmurff"
		},
		"retweet_count": 0,
		"id": "661478494338162689",
		"favorite_count": 0
	},
	{
		"text": "#rbtv #moinmoin pizza geht immer! Pizza ist #geili",
		"created_at": 1446543767,
		"user": {
			"id": "1603343702",
			"name": "pizzamel"
		},
		"retweet_count": 0,
		"id": "661478619445882880",
		"favorite_count": 0
	},
	{
		"text": "#moinmoin #rbtv #geili #RaspberryPi #fhem https://t.co/j3oQhDaAIE",
		"created_at": 1446543782,
		"user": {
			"id": "37655507",
			"name": "Crush85"
		},
		"retweet_count": 0,
		"id": "661478685124526080",
		"favorite_count": 0
	},
	{
		"text": "Gregott du #Geili #Geili #Supertyp #rbtv",
		"created_at": 1446543786,
		"user": {
			"id": "376705860",
			"name": "MasterFarr"
		},
		"retweet_count": 0,
		"id": "661478701784256512",
		"favorite_count": 0
	},
	{
		"text": "#rbtv #moinmoin langweiligste vorlesung ever. Abee immerhin moinmooin #geili",
		"created_at": 1446543795,
		"user": {
			"id": "382285226",
			"name": "dominikd1"
		},
		"retweet_count": 0,
		"id": "661478737431646208",
		"favorite_count": 0
	},
	{
		"text": "Oh, ich hatte Wrestling Face verstanden. :(\n#rbtv #moinmoin #geili",
		"created_at": 1446543829,
		"user": {
			"id": "221534796",
			"name": "AnkheeTheMonkee"
		},
		"retweet_count": 0,
		"id": "661478879471796224",
		"favorite_count": 0
	},
	{
		"text": "Mama ! Papa ! Ich war Kurz im Fernseh :D #rbtv #moinmoin #geili #Binichimfernseh  Danke Gregor :P https://t.co/HzMsdWbvMQ",
		"created_at": 1446543844,
		"user": {
			"id": "2981523053",
			"name": "K3nJi87"
		},
		"retweet_count": 0,
		"id": "661478942700883968",
		"favorite_count": 0
	},
	{
		"text": "Freund bemerkte grade, dass @Chaz_Ashley sich heute rasiert hat, gestern bei #wmr war noch mehr Bart. #rbtv #moinmoin #geili",
		"created_at": 1446543850,
		"user": {
			"id": "2563816790",
			"name": "FrauNasenbaer"
		},
		"retweet_count": 0,
		"id": "661478967535243266",
		"favorite_count": 0
	},
	{
		"text": "Ich hab ein bitchy resting face wenn ich Fahrrad fahre. Da gucke ich immer ganz b\u00f6se :( \n\n#rbtv #geili #moinmoin",
		"created_at": 1446543868,
		"user": {
			"id": "2389042604",
			"name": "Creeveey"
		},
		"retweet_count": 0,
		"id": "661479045411045376",
		"favorite_count": 3
	},
	{
		"text": "Oh ja meine Freundin hat ein wirklich schlimmes bitchy resting face. Man hat das Gef\u00fchl, sie m\u00f6chte einen ermorden xD #moinmoin #rbtv #geili",
		"created_at": 1446543879,
		"user": {
			"id": "91597195",
			"name": "Phoenix_Legion"
		},
		"retweet_count": 0,
		"id": "661479091611258880",
		"favorite_count": 0
	},
	{
		"text": "Best Moment at B.E.A.R.D.S. #moinmoin #rbtv #geili https://t.co/0RYqxBQmGM",
		"created_at": 1446543882,
		"user": {
			"id": "3027955228",
			"name": "DonThePein"
		},
		"retweet_count": 0,
		"id": "661479101493067776",
		"favorite_count": 0
	},
	{
		"text": "#moinmoin #rbtv #geili mitten in der Nacht auf Hawaii, aber moinmoin mit Gregor geht zu jeder Uhrzeit",
		"created_at": 1446543891,
		"user": {
			"id": "2541077557",
			"name": "sven_kaufmann"
		},
		"retweet_count": 0,
		"id": "661479142009933824",
		"favorite_count": 0
	},
	{
		"text": "Cool, heute ist @Gronkh bei den @TheRocketBeans zu Besuch \ud83d\ude02\ud83d\ude02\n#rbtv #moinmoin https://t.co/fC6aZ77OVn",
		"created_at": 1446543892,
		"user": {
			"id": "265068407",
			"name": "WassiaEichhorn"
		},
		"retweet_count": 0,
		"id": "661479143264157696",
		"favorite_count": 0
	},
	{
		"text": "Und @Gronkh ist auch einfach mal in Bildform bei @TheRocketBeans :D #moinmoin #rbtv #geili",
		"created_at": 1446543958,
		"user": {
			"id": "2563816790",
			"name": "FrauNasenbaer"
		},
		"retweet_count": 0,
		"id": "661479420117389313",
		"favorite_count": 0
	},
	{
		"text": "endlich wieder moinmoin mit alwin #rbtv #moinmoin #geili",
		"created_at": 1446544002,
		"user": {
			"id": "2388027984",
			"name": "Garentier"
		},
		"retweet_count": 0,
		"id": "661479606944440321",
		"favorite_count": 0
	},
	{
		"text": "Mein Ziegenbock has all the honey in the pot. #geili #rbtv #moinmoin",
		"created_at": 1446544046,
		"user": {
			"id": "42664964",
			"name": "tbstbstbs"
		},
		"retweet_count": 0,
		"id": "661479792303280128",
		"favorite_count": 0
	},
	{
		"text": "Gregor mit einem Bullet Club Shirt? #RBTV #geili #moinmoin",
		"created_at": 1446544066,
		"user": {
			"id": "774073250",
			"name": "takenoyujin"
		},
		"retweet_count": 0,
		"id": "661479876273270784",
		"favorite_count": 0
	},
	{
		"text": "Ist das nicht #geili ! kennst du ja auch :P .Was man so wiederfindet !  #moinmoin #rbtv #dbz https://t.co/WhzCmn1B9q",
		"created_at": 1446544108,
		"user": {
			"id": "2981523053",
			"name": "K3nJi87"
		},
		"retweet_count": 0,
		"id": "661480052614393856",
		"favorite_count": 0
	},
	{
		"text": "#rbtv #geili #moinmoin gregor wo hast du dein bullet club shirt her?",
		"created_at": 1446544109,
		"user": {
			"id": "3027944813",
			"name": "DevilsGame666"
		},
		"retweet_count": 0,
		"id": "661480053222588416",
		"favorite_count": 0
	},
	{
		"text": "Bin ich das oder sieht das Kind aus wie @Colin_Gaebel? :D \n#rbtv #rocketbeans @TheRocketBeans https://t.co/ogC7kQa3Ip",
		"created_at": 1446544147,
		"user": {
			"id": "968875902",
			"name": "shynarja"
		},
		"retweet_count": 0,
		"id": "661480214292246528",
		"favorite_count": 1
	},
	{
		"text": "gregors crazy restface :D #rbtv #moinmoin https://t.co/hOitOCfLXT",
		"created_at": 1446544184,
		"user": {
			"id": "1452300852",
			"name": "Mathias_Strato"
		},
		"retweet_count": 0,
		"id": "661480370257436672",
		"favorite_count": 0
	},
	{
		"text": "Kylie Minogue + Gregott. #rbtv #moinmoin #geili https://t.co/0NHNxLb8ii",
		"created_at": 1446544248,
		"user": {
			"id": "97406649",
			"name": "Stuessy79"
		},
		"retweet_count": 0,
		"id": "661480638302785536",
		"favorite_count": 3
	},
	{
		"text": "#Pokemon cassix mit @EtienneToGo ist mit Abstand das unterhaltsamste was die Medienlandschaft zur Zeit zu bieten hat! Danke! #rbtv #classix",
		"created_at": 1446544394,
		"user": {
			"id": "1129542560",
			"name": "Maehx89"
		},
		"retweet_count": 0,
		"id": "661481251547824128",
		"favorite_count": 2
	},
	{
		"text": "Gregor nimmt sich frei...wegen Madonna? Und bezahlt daf\u00fcr auch noch? \ud83d\ude02\ud83d\ude02\ud83d\ude02\ud83d\ude02 #geili #RBTV #moinmoin",
		"created_at": 1446544441,
		"user": {
			"id": "774073250",
			"name": "takenoyujin"
		},
		"retweet_count": 0,
		"id": "661481449401503744",
		"favorite_count": 0
	},
	{
		"text": "#MoinMoin #rbtv \nMoin Gregor, liebe Gr\u00fc\u00dfe! https://t.co/kFuJo2FLqL",
		"created_at": 1446544459,
		"user": {
			"id": "3329080504",
			"name": "OriJohann"
		},
		"retweet_count": 0,
		"id": "661481524789948416",
		"favorite_count": 0
	},
	{
		"text": "Ich bin dezent neidisch, dass @Chaz_Ashley zu #WWELeipzig f\u00e4hrt. Ich m\u00f6chte auch :C #rbtv #moinmoin #geili",
		"created_at": 1446544520,
		"user": {
			"id": "2563816790",
			"name": "FrauNasenbaer"
		},
		"retweet_count": 1,
		"id": "661481778780069888",
		"favorite_count": 0
	},
	{
		"text": "Kurze Pause f\u00fcr #moinmoin #geili #rbtv https://t.co/8dONlZeJ7I",
		"created_at": 1446544533,
		"user": {
			"id": "544629867",
			"name": "EnricoGlaser"
		},
		"retweet_count": 0,
		"id": "661481833994002432",
		"favorite_count": 2
	},
	{
		"text": "@Chaz_Ashley dein Beitrag f\u00fcr die News heute ist bestimmt die neue Star Trek Serie 2017? :) #geili #moinmoin #rbtv https://t.co/IoRSCVjL1n",
		"created_at": 1446544587,
		"user": {
			"id": "3029949971",
			"name": "Deet_C"
		},
		"retweet_count": 0,
		"id": "661482061706956800",
		"favorite_count": 0
	},
	{
		"text": "War bei Moneyboy, das ist auch fast wie ein Madonna Konzert! #moinmoin #rbtv #geili",
		"created_at": 1446544620,
		"user": {
			"id": "101027596",
			"name": "KefkaRulez"
		},
		"retweet_count": 0,
		"id": "661482196801335296",
		"favorite_count": 0
	},
	{
		"text": "Samy Deluxe damals 2001 bei Rock am Ring.\nSonst das Gr\u00f6\u00dfte waren wohl 2x die Beastie Boys. \u2665\n#rbtv #moinmoin #geili",
		"created_at": 1446544637,
		"user": {
			"id": "221534796",
			"name": "AnkheeTheMonkee"
		},
		"retweet_count": 0,
		"id": "661482268209364992",
		"favorite_count": 0
	},
	{
		"text": "Warten immer noch auf die SCOUTS VS. ZOMBIES Ticket Gewinner! Ihr habt ne private Twitter Nachricht!  #rbtv #151115 https://t.co/DPpK0uP4Ua",
		"created_at": 1446544751,
		"user": {
			"id": "370029585",
			"name": "TheRocketBeans"
		},
		"retweet_count": 7,
		"id": "661482745865064448",
		"favorite_count": 58
	},
	{
		"text": "@TheRocketBeans Gregor du Banane, #Enterprise war nach DS9 die erste Star Trek Serie #RBTV #geili #moinmoin",
		"created_at": 1446544764,
		"user": {
			"id": "774073250",
			"name": "takenoyujin"
		},
		"retweet_count": 0,
		"id": "661482804304310272",
		"favorite_count": 0
	},
	{
		"text": "#rbtv in der Pr\u00fcfungsvorbereitung f\u00fcr Abschlusspr\u00fcfung teil 2 zur industriemechanikerin sitzen. Kann mir sch\u00f6neres vorstellen.",
		"created_at": 1446544767,
		"user": {
			"id": "3374466627",
			"name": "Stahlarbeiterin"
		},
		"retweet_count": 0,
		"id": "661482814974656512",
		"favorite_count": 3
	},
	{
		"text": "#rbtv #geili #moinmoin https://t.co/PbUsjCOzZp",
		"created_at": 1446544770,
		"user": {
			"id": "3159620753",
			"name": "5huya"
		},
		"retweet_count": 0,
		"id": "661482828744495104",
		"favorite_count": 0
	},
	{
		"text": "Zur\u00fcck in die Vergangenheit war eine total tolle Serie :3 #rbtv #moinmoin #geili",
		"created_at": 1446544773,
		"user": {
			"id": "2563816790",
			"name": "FrauNasenbaer"
		},
		"retweet_count": 0,
		"id": "661482842220838912",
		"favorite_count": 0
	},
	{
		"text": "Enterprise hatte seine Momente. Ihr m\u00fcsst mal Teil3 vom Star Trek Podcast mit Community machen ;) @Chaz_Ashley #rbtv #geili #moinmoin",
		"created_at": 1446544804,
		"user": {
			"id": "3029949971",
			"name": "Deet_C"
		},
		"retweet_count": 0,
		"id": "661482968528068608",
		"favorite_count": 0
	},
	{
		"text": "#Moinmoin #rbtv #geili StarDRECK hab ich nie verfolgt sag doch lieber mal wann Dragonball Super nach Deutschland, kommt das weisst du doch.",
		"created_at": 1446544833,
		"user": {
			"id": "2678139115",
			"name": "Hahninger"
		},
		"retweet_count": 0,
		"id": "661483091366670336",
		"favorite_count": 0
	},
	{
		"text": "#rbtv #moinmoin #geili\nIch bin lieb, ihr seid alle b\u00f6s!! https://t.co/Co6GETRCH0",
		"created_at": 1446544901,
		"user": {
			"id": "221534796",
			"name": "AnkheeTheMonkee"
		},
		"retweet_count": 0,
		"id": "661483378240307200",
		"favorite_count": 2
	},
	{
		"text": "One-Punch-Gregott @Chaz_Ashley @TheRocketBeans #moinmoin #rbtv #geili https://t.co/kMu0NVhxF8",
		"created_at": 1446545036,
		"user": {
			"id": "2923002226",
			"name": "BohnLui"
		},
		"retweet_count": 1,
		"id": "661483942948806657",
		"favorite_count": 4
	},
	{
		"text": "#rbtv #geili #moinmoin https://t.co/vyUssU9bAa",
		"created_at": 1446545062,
		"user": {
			"id": "135870966",
			"name": "nVoidRayy"
		},
		"retweet_count": 0,
		"id": "661484050989883392",
		"favorite_count": 3
	},
	{
		"text": "#moinmoin #geili #rbtv\n\nGreg kannst du nicht mal Tales of Zestiria auf rbtv spielen?",
		"created_at": 1446545079,
		"user": {
			"id": "3390654135",
			"name": "HerrGeilen"
		},
		"retweet_count": 0,
		"id": "661484122301456384",
		"favorite_count": 2
	},
	{
		"text": "#geili  hier ist mein Bart nachtr\u00e4glich #rbtv  #moinmoin https://t.co/YSWAA0O4u7",
		"created_at": 1446545230,
		"user": {
			"id": "1702822171",
			"name": "DerSmurff"
		},
		"retweet_count": 0,
		"id": "661484755163172864",
		"favorite_count": 0
	},
	{
		"text": "Einschr\u00e4nkungen beim Ton? #NichtMitKrogmann! Heute neue Kabel und morgen die Weltherrschaft. #rbtv @MrCrackerMicha",
		"created_at": 1446545275,
		"user": {
			"id": "3028799397",
			"name": "TechInterMezzo"
		},
		"retweet_count": 0,
		"id": "661484945588776960",
		"favorite_count": 2
	},
	{
		"text": "Besser als jedes Madonna Konzert oder Legend of Zelda Konzert ist Video Gamers live wo ich war *-* #moinmoin #rbtv #geili",
		"created_at": 1446545428,
		"user": {
			"id": "2872548023",
			"name": "H_RJay"
		},
		"retweet_count": 0,
		"id": "661485589116624897",
		"favorite_count": 2
	},
	{
		"text": "@TheRocketBeans n\u00f6 hab keine. \n\nWar kleines sp\u00e4ssien gl\u00fcckwunsch an die gewinner :) #rbtv #moinmoin",
		"created_at": 1446545513,
		"user": {
			"id": "2481369136",
			"name": "guybrushfreeman"
		},
		"retweet_count": 0,
		"id": "661485943224934400",
		"favorite_count": 0
	},
	{
		"text": "Ich find das neue Moin Moin Studio n bisschen zu dunkel. @TheRocketBeans #rbtv #moinmoin",
		"created_at": 1446545565,
		"user": {
			"id": "332692319",
			"name": "counterfirst"
		},
		"retweet_count": 0,
		"id": "661486161035198464",
		"favorite_count": 1
	},
	{
		"text": "Ich liebe das MoinMoin mit Gregor :D #Geili #MoinMoin #rbtv",
		"created_at": 1446545589,
		"user": {
			"id": "252218696",
			"name": "RabuMia"
		},
		"retweet_count": 0,
		"id": "661486262537293824",
		"favorite_count": 2
	},
	{
		"text": "Und das war #moinmoin mit @Chaz_Ashley aus einem schwarzen Loch, der Negativzone oder was-auch-immer. Etwas unbehaglich. #rbtv #geili",
		"created_at": 1446545924,
		"user": {
			"id": "3014922071",
			"name": "Kronbaer"
		},
		"retweet_count": 0,
		"id": "661487668895727616",
		"favorite_count": 0
	},
	{
		"text": "#rbtv #moinmoin #geili @Chaz_Ashley  @Colin_Gaebel \nEm-EuColin! https://t.co/WpN7B5IX01",
		"created_at": 1446545994,
		"user": {
			"id": "2204843160",
			"name": "DTVCoppelius"
		},
		"retweet_count": 9,
		"id": "661487963193409536",
		"favorite_count": 144
	},
	{
		"text": "#rbtv @TheRocketBeans omg Gregor Live getroffen https://t.co/00Vbhax2hh",
		"created_at": 1446546430,
		"user": {
			"id": "3043005170",
			"name": "crockett664"
		},
		"retweet_count": 0,
		"id": "661489791733747712",
		"favorite_count": 2
	},
	{
		"text": "#rbtv @TheRocketBeans \u00fcber 200 Kilometer gefahren und dann nicht getraut zu klingeln \ud83d\ude0c",
		"created_at": 1446547510,
		"user": {
			"id": "3043005170",
			"name": "crockett664"
		},
		"retweet_count": 1,
		"id": "661494319161999360",
		"favorite_count": 1
	},
	{
		"text": "Auch sehr sehenswert @MoritzBleibtreu bei @TheRocketBeans #rbtv https://t.co/HuHTTKG9Gt\n https://t.co/qsSE7q4WWL",
		"created_at": 1446547901,
		"user": {
			"id": "194391911",
			"name": "Marco_W_S"
		},
		"retweet_count": 0,
		"id": "661495959977857024",
		"favorite_count": 3
	},
	{
		"text": "Da looten @EduardLeser &amp; @DJ_KingKlik (Basti!) einfach unser Wohnzimmer! #rbtv #moinmoin #151115 https://t.co/oc5oxxsV96",
		"created_at": 1446548024,
		"user": {
			"id": "370029585",
			"name": "TheRocketBeans"
		},
		"retweet_count": 13,
		"id": "661496475407486976",
		"favorite_count": 154
	},
	{
		"text": "Die Bohnen reden im Almost Daily \u00fcber das Sub in der Altstadt. Schlimme Erinnerungen an Karneval 2014, uiuiuiu. \n\n#rbtv #almostdaily",
		"created_at": 1446548134,
		"user": {
			"id": "2389042604",
			"name": "Creeveey"
		},
		"retweet_count": 0,
		"id": "661496935480733696",
		"favorite_count": 2
	},
	{
		"text": "ich war auch bei der bundeswehr und wenn Banker wirklich mehr saufen als beim Bund dann oha oha oha :D #rbtv",
		"created_at": 1446549057,
		"user": {
			"id": "166899533",
			"name": "Rattleraptor82"
		},
		"retweet_count": 0,
		"id": "661500809297854468",
		"favorite_count": 1
	},
	{
		"text": "Der @Ginosaurier und @Lugetersch schreiben sich noch Gedichte bis die #almostplaily Aufzeichnung beginnt. #rbtv https://t.co/yLf5w1T1Bg",
		"created_at": 1446549859,
		"user": {
			"id": "370029585",
			"name": "TheRocketBeans"
		},
		"retweet_count": 2,
		"id": "661504172873916416",
		"favorite_count": 91
	},
	{
		"text": "Etienne Gard\u00e9: About Bratpfanns :) #rbtv\nhttps://t.co/M56ZlYoTYh https://t.co/uIABZr9fl8",
		"created_at": 1446550982,
		"user": {
			"id": "463748542",
			"name": "Moon_N7"
		},
		"retweet_count": 1,
		"id": "661508882708226048",
		"favorite_count": 3
	},
	{
		"text": "Das #MoinMoin k\u00f6nnte etwas sp\u00e4ter kommen, da immer noch vielen von #vault404 hochgeladen wird. :D #rbtv https://t.co/HG6tMbJtJo",
		"created_at": 1446551907,
		"user": {
			"id": "1557883806",
			"name": "MarcoGiesel"
		},
		"retweet_count": 1,
		"id": "661512760480702464",
		"favorite_count": 27
	},
	{
		"text": "Macht aus ihren kleinen Lauch, einen Laser #rbtv #laser https://t.co/yb3TiKN6UL",
		"created_at": 1446553754,
		"user": {
			"id": "3377952387",
			"name": "EduardLaserToGo"
		},
		"retweet_count": 1,
		"id": "661520507985125376",
		"favorite_count": 11
	},
	{
		"text": "ENDLICH B.E.A.R.D.S. Akt 2 nachholen :) #rbtv #spitzestifte https://t.co/4li4NfLmki",
		"created_at": 1446554013,
		"user": {
			"id": "3244078468",
			"name": "JayRod1991"
		},
		"retweet_count": 0,
		"id": "661521597090656257",
		"favorite_count": 0
	},
	{
		"text": "@EduardLaserToGo Sind Sie zu Laser, bist du zu Lauch #rbtv #laser",
		"created_at": 1446554087,
		"user": {
			"id": "3599130029",
			"name": "ShiefmasterNo1"
		},
		"retweet_count": 0,
		"id": "661521906873573376",
		"favorite_count": 5
	},
	{
		"text": "Mit @Gunnsen @quarkophag @Ginosaurier und @Lugetersch eines der vermutlich lustigsten Plailys aufgenommen. Seid gespannt! #rbtv #impro",
		"created_at": 1446555908,
		"user": {
			"id": "448098258",
			"name": "Darantino"
		},
		"retweet_count": 4,
		"id": "661529541886795776",
		"favorite_count": 63
	},
	{
		"text": "@Darantino @Gunnsen @quarkophag @Ginosaurier @Lugetersch war @Pun_der_Zar etwa das spielger\u00e4t? #rbtv",
		"created_at": 1446556035,
		"user": {
			"id": "2806977000",
			"name": "cerbilicious"
		},
		"retweet_count": 0,
		"id": "661530078434754560",
		"favorite_count": 0
	},
	{
		"text": "@c_stra @TheRocketBeans \nDieser Chrisitan Stra\u00dfenburger Moment, wenn man aussieht wie Hans Entertainment #sotrue #rbtv #Bohndesliga",
		"created_at": 1446556970,
		"user": {
			"id": "2182314690",
			"name": "Profitipps"
		},
		"retweet_count": 0,
		"id": "661533996099194884",
		"favorite_count": 0
	},
	{
		"text": "Auf #gameplus mit @MoritzBleibtreu \"Lammbock\" nachgeholt. Gem\u00fctl. Buddy-Kom\u00f6die mit gef\u00e4lliger Jay &amp; Silent Bob-Referenz. \ud83d\ude00 #kinoplus #rbtv",
		"created_at": 1446557254,
		"user": {
			"id": "3014922071",
			"name": "Kronbaer"
		},
		"retweet_count": 0,
		"id": "661535191018655744",
		"favorite_count": 1
	},
	{
		"text": "So wird es mir wahrscheinlich auch gehen, wenn ich 'Life Is Strange' weiterspiele... https://t.co/ISLXAgG5IF #LifeIsStrange #RBTV",
		"created_at": 1446557628,
		"user": {
			"id": "65011153",
			"name": "M_Weyland"
		},
		"retweet_count": 0,
		"id": "661536757742219264",
		"favorite_count": 1
	},
	{
		"text": "Whaaat, is this true? \ud83d\ude31 #rbtv #kinoplus \n@LeSchroeck @badeboom https://t.co/R9VobOPZMc",
		"created_at": 1446557883,
		"user": {
			"id": "3392232909",
			"name": "tason_jodd"
		},
		"retweet_count": 0,
		"id": "661537826748669952",
		"favorite_count": 0
	},
	{
		"text": "30 nov: Erkende taaltoets Nederlands C1 #tolk #vertaler #Rbtv  https://t.co/K8wkp4uVXg #tolken #xl8",
		"created_at": 1446559387,
		"user": {
			"id": "106072939",
			"name": "TolkenSelect"
		},
		"retweet_count": 0,
		"id": "661544136508510208",
		"favorite_count": 0
	},
	{
		"text": "@GameOvermeier @TheRocketBeans was ne Nachmacher #rbtv #sexyHauke",
		"created_at": 1446559593,
		"user": {
			"id": "884963762",
			"name": "Maxlampi"
		},
		"retweet_count": 0,
		"id": "661544998463266816",
		"favorite_count": 0
	},
	{
		"text": "@TheRocketBeans @LeSchroeck @Lugetersch Beans vs. Lego Round2 ? #rbtv https://t.co/UYwh0yvF0A",
		"created_at": 1446561666,
		"user": {
			"id": "988168081",
			"name": "BeefSteve"
		},
		"retweet_count": 0,
		"id": "661553692894765058",
		"favorite_count": 1
	},
	{
		"text": "Wird @DerHauge seine Kuh-Attraktion beenden &amp; wie geht es auf Skarnland weiter? Erfahrt es ab 18 Uhr bei @TheRocketBeans #rbtv #Rocketminers",
		"created_at": 1446562483,
		"user": {
			"id": "3382808505",
			"name": "RocketMiners"
		},
		"retweet_count": 7,
		"id": "661557122753298433",
		"favorite_count": 30
	},
	{
		"text": "\"Ein Hacker ohne Kaffee ist wie eine Mutter ohne Morgenr\u00f6te\" (Sofia Kats, 2015) #rbtv xD\n@artsykatsy @TheRocketBeans",
		"created_at": 1446563506,
		"user": {
			"id": "3113996163",
			"name": "BigRBean"
		},
		"retweet_count": 1,
		"id": "661561411357773824",
		"favorite_count": 3
	},
	{
		"text": "@maexdaemaege du pr0-haxxor :-P hast du informatik studiert oder warum bist du bei #rbtv der \"Hacker\" :-D",
		"created_at": 1446563506,
		"user": {
			"id": "3222532908",
			"name": "XxK1llu4xX"
		},
		"retweet_count": 0,
		"id": "661561413563977728",
		"favorite_count": 0
	},
	{
		"text": "@TheRocketBeans hab zur\u00fcck geschrieben! #ScoutsVsZombies #rbtv",
		"created_at": 1446563705,
		"user": {
			"id": "742363291",
			"name": "Eppi_DE"
		},
		"retweet_count": 0,
		"id": "661562248452771840",
		"favorite_count": 0
	},
	{
		"text": "Die @TheRocketBeans #Rocketbeats #21 f\u00fcr #GoogleMusic verz\u00f6gert sich leider aus beruflichen Gr\u00fcnden bis Freitag.\nGr\u00fc\u00dfe aus Frankreich\n#rbtv",
		"created_at": 1446563855,
		"user": {
			"id": "104452756",
			"name": "Soonic6"
		},
		"retweet_count": 0,
		"id": "661562875824197632",
		"favorite_count": 0
	},
	{
		"text": "Moment. L\u00e4uft der Stream noch? Unser #kabelking hat n\u00e4mlich Pause! #rbtv #151115 https://t.co/gt5JJWgb3i",
		"created_at": 1446564739,
		"user": {
			"id": "370029585",
			"name": "TheRocketBeans"
		},
		"retweet_count": 3,
		"id": "661566581575675904",
		"favorite_count": 134
	},
	{
		"text": "Profihacker, da schaut man gerne zu :D #rbtv\n@TheRocketBeans  @maexdaemaege  @Gunnsen https://t.co/h0I0AcRC15",
		"created_at": 1446566200,
		"user": {
			"id": "3113996163",
			"name": "BigRBean"
		},
		"retweet_count": 0,
		"id": "661572711647461376",
		"favorite_count": 2
	},
	{
		"text": "\"Lennard? Ich bin krank\" und das auch noch in meinem Urlaub. @TheRocketBeans ihr wisst was zu tun ist. Unterhaltet mich.\u270c\ud83d\ude91\ud83c\udfe5 #rbtv",
		"created_at": 1446566407,
		"user": {
			"id": "3319261849",
			"name": "citynightknight"
		},
		"retweet_count": 0,
		"id": "661573581395116032",
		"favorite_count": 0
	},
	{
		"text": "Herzen finden wir gut. Sofia meint: \"Geht so.\" Zeigt uns doch auch eure Gesichter dazu. #tweetsoflove #rbtv https://t.co/pbdoq41GYx",
		"created_at": 1446566858,
		"user": {
			"id": "370029585",
			"name": "TheRocketBeans"
		},
		"retweet_count": 8,
		"id": "661575470056660992",
		"favorite_count": 187
	},
	{
		"text": "YES. \n\n#rbtv #bahnparty #plauschangriff https://t.co/tzIU3Qy3oR",
		"created_at": 1446566980,
		"user": {
			"id": "2389042604",
			"name": "Creeveey"
		},
		"retweet_count": 0,
		"id": "661575982034395136",
		"favorite_count": 8
	},
	{
		"text": "#rbtv  Welcher neue Trailer hat es euch angetan? Oder feiert ihr einfach nur einen alten Trailer ab, den ihr heute\u2026 https://t.co/W6VjInjAWP",
		"created_at": 1446567409,
		"user": {
			"id": "3017523491",
			"name": "rbtvcommunity"
		},
		"retweet_count": 0,
		"id": "661577784444088320",
		"favorite_count": 0
	},
	{
		"text": "#rbtv Gunnar, stell auf Langsam",
		"created_at": 1446567990,
		"user": {
			"id": "780159806",
			"name": "DaveK222"
		},
		"retweet_count": 0,
		"id": "661580217476128768",
		"favorite_count": 0
	},
	{
		"text": "Mh, vllt. versuche ich es nun t\u00e4glich: Spielen einige aus der #rbtv // @TheRocketBeans-Community/Familie #Warframe auf dem PC? Cheers. (:",
		"created_at": 1446568525,
		"user": {
			"id": "339088850",
			"name": "Dan_Morgenstern"
		},
		"retweet_count": 0,
		"id": "661582462984790016",
		"favorite_count": 0
	},
	{
		"text": "Emergency 2016 + @Gunnsen = unfreiwillig saukomisch. #rbtv",
		"created_at": 1446568945,
		"user": {
			"id": "3028799397",
			"name": "TechInterMezzo"
		},
		"retweet_count": 0,
		"id": "661584223334211585",
		"favorite_count": 1
	},
	{
		"text": "Emergency 2016 sieht ja richtig realistisch aus! Einfach Schlauch an den Hydranten ein Mann vorne ran und ab geht das L\u00f6schen! #rbtv #zmb",
		"created_at": 1446569357,
		"user": {
			"id": "2183990136",
			"name": "SKoch91"
		},
		"retweet_count": 0,
		"id": "661585954751254534",
		"favorite_count": 0
	},
	{
		"text": "Emergency mit @Gunnsen war so \u00fcberragend :D #rbtv",
		"created_at": 1446569992,
		"user": {
			"id": "55363687",
			"name": "ethanhawkman"
		},
		"retweet_count": 0,
		"id": "661588617664577536",
		"favorite_count": 1
	},
	{
		"text": "@TheRocketBeans @DerHauge aw da steht mein kleiner r2d2 \u2764\u2764 #rbtv #rocketminers \nkann heute leider nicht mitbauen :/ https://t.co/b5mLcvRWA5",
		"created_at": 1446570410,
		"user": {
			"id": "947462989",
			"name": "Minaru92"
		},
		"retweet_count": 0,
		"id": "661590367784054785",
		"favorite_count": 0
	},
	{
		"text": "Einschalten oder sterben! #151115 #rbtv",
		"created_at": 1446571296,
		"user": {
			"id": "106636023",
			"name": "TRIEBKRAFT"
		},
		"retweet_count": 0,
		"id": "661594084432150528",
		"favorite_count": 0
	},
	{
		"text": "Ich schmei\u00df mich weg. Wie gut sind denn die Lieder \ud83d\ude02 #rbtv #rocketminers",
		"created_at": 1446572263,
		"user": {
			"id": "2730964882",
			"name": "Samara_Slow"
		},
		"retweet_count": 0,
		"id": "661598140945051648",
		"favorite_count": 1
	},
	{
		"text": "Ich finde den Namen \"Hauke\" ganz gut! #rbtv #rocketminers #seinnichttraurighauke :D :D :D",
		"created_at": 1446572354,
		"user": {
			"id": "2212279326",
			"name": "monercuron"
		},
		"retweet_count": 0,
		"id": "661598523306176512",
		"favorite_count": 0
	},
	{
		"text": "#rbtv Mich beschleicht das Gef\u00fchl, das jemand zu tief in die Hustensaftflasche geschaut hat! :D  #rocketminers",
		"created_at": 1446572773,
		"user": {
			"id": "3323646605",
			"name": "ApoRuebli"
		},
		"retweet_count": 0,
		"id": "661600281705193475",
		"favorite_count": 1
	},
	{
		"text": "@DerHauge  Jetzt Eskalierts ! aber ich finds geil ! #rbtv  #rocketminers \nDrogen und Gewalt und son kram",
		"created_at": 1446572871,
		"user": {
			"id": "3068789301",
			"name": "Bohne_117"
		},
		"retweet_count": 0,
		"id": "661600692973477888",
		"favorite_count": 0
	},
	{
		"text": "#RBTV - Nils &amp; Eddy - Best of Pokemon Feuerrot https://t.co/tLNCEx5C6f via @YouTube #eddy der gr\u00f6sste pokemon experte der welt #24hpokemon",
		"created_at": 1446572915,
		"user": {
			"id": "2803292570",
			"name": "DeFuchss"
		},
		"retweet_count": 0,
		"id": "661600876671430656",
		"favorite_count": 0
	},
	{
		"text": "Ah, @DerHauge ist auf Speed. :D Das erkl\u00e4rt einiges!\n#rbtv #rocketminers #klotzen https://t.co/Jvct8tdka7",
		"created_at": 1446573052,
		"user": {
			"id": "221534796",
			"name": "AnkheeTheMonkee"
		},
		"retweet_count": 1,
		"id": "661601451408498688",
		"favorite_count": 4
	},
	{
		"text": "@DerHauge Danke f\u00fcr die lustige Runde #Minecraft! #rbtv  XD",
		"created_at": 1446573285,
		"user": {
			"id": "3152187581",
			"name": "Ozelot003"
		},
		"retweet_count": 0,
		"id": "661602426915561472",
		"favorite_count": 0
	},
	{
		"text": "#SexyHauke\n#lippenbefeuchten #beards\n#rbtv #klotzen #rocketminers https://t.co/U6Wfs1Ix4Y",
		"created_at": 1446573579,
		"user": {
			"id": "221534796",
			"name": "AnkheeTheMonkee"
		},
		"retweet_count": 0,
		"id": "661603663102767104",
		"favorite_count": 1
	},
	{
		"text": "Was ist heute eigentlich mit Hauke los?! \ud83d\ude04 #rbtv #rocketminers",
		"created_at": 1446573593,
		"user": {
			"id": "341108999",
			"name": "Seasick_Heart"
		},
		"retweet_count": 0,
		"id": "661603720120004608",
		"favorite_count": 2
	},
	{
		"text": "Heute angekommen. Ich verlass mich auf euch #rbtv #buchclub https://t.co/gmHFXEBYJ1",
		"created_at": 1446573897,
		"user": {
			"id": "2990353047",
			"name": "KonstantinLutz"
		},
		"retweet_count": 0,
		"id": "661604993221423104",
		"favorite_count": 0
	},
	{
		"text": "Ich schau seit 1Min. #rbtv und @derhauge disst Kollegen schaut auf https://t.co/0jMw0y56rC \n\nGenau deshalb liebe ich RocketBeans &lt;3",
		"created_at": 1446574350,
		"user": {
			"id": "2327508482",
			"name": "PeterKonditor"
		},
		"retweet_count": 0,
		"id": "661606896827244544",
		"favorite_count": 4
	},
	{
		"text": "Welche Medizin nimmt Hauke und wo bekomme ich die?\n#rbtv #rocketminers #klotzen",
		"created_at": 1446574439,
		"user": {
			"id": "221534796",
			"name": "AnkheeTheMonkee"
		},
		"retweet_count": 0,
		"id": "661607266269925376",
		"favorite_count": 0
	},
	{
		"text": "@DerHauge Heute in hochform ey genial #rbtv #rocketminers",
		"created_at": 1446574462,
		"user": {
			"id": "3068789301",
			"name": "Bohne_117"
		},
		"retweet_count": 0,
		"id": "661607365037420544",
		"favorite_count": 1
	},
	{
		"text": "Forever alone. - mit Handcreme. #rbtv #rocketminers",
		"created_at": 1446574476,
		"user": {
			"id": "56374732",
			"name": "kaltric"
		},
		"retweet_count": 0,
		"id": "661607423615098880",
		"favorite_count": 0
	},
	{
		"text": "\"Wirf alle Hoffnungen \u00fcber Bord und hol die Handcreme raus\" - @DerHauge , 2015 #rbtv #rocketminers",
		"created_at": 1446574492,
		"user": {
			"id": "52530939",
			"name": "theannoyingmatz"
		},
		"retweet_count": 2,
		"id": "661607490769981441",
		"favorite_count": 21
	},
	{
		"text": "W\u00fcrde Hauke ne Dating Plattform leiten , w\u00fcrde sich alle 11Minuten jemand trennen.\n\n#rbtv",
		"created_at": 1446574603,
		"user": {
			"id": "2327508482",
			"name": "PeterKonditor"
		},
		"retweet_count": 0,
		"id": "661607958170746880",
		"favorite_count": 7
	},
	{
		"text": "Wenn man von Dorian Gray redet und die Leute denken es geht um 50 shades... \ud83d\ude22 @TheRocketBeans #rbtv #buchklub",
		"created_at": 1446574629,
		"user": {
			"id": "2770621591",
			"name": "Murmelmaus05"
		},
		"retweet_count": 0,
		"id": "661608066161446912",
		"favorite_count": 0
	},
	{
		"text": "Liebe @TheRocketBeans, gebt @DerHauge mal bitte Zucker in irgendeiner Form. Ich glaub sein Blutzuckerlevel ist zu niedrig #rbtv",
		"created_at": 1446574960,
		"user": {
			"id": "908130818",
			"name": "corky869"
		},
		"retweet_count": 0,
		"id": "661609454945873920",
		"favorite_count": 2
	},
	{
		"text": "Einfach mal f\u00fcr alles Danke sagen!\n@TheRocketBeans #rbtv",
		"created_at": 1446575082,
		"user": {
			"id": "3382171456",
			"name": "Aquila_Magician"
		},
		"retweet_count": 0,
		"id": "661609966260891648",
		"favorite_count": 1
	},
	{
		"text": "So! Pok\u00e9mon ist online! Lauchboy ist bereit! #rbtv #seikeindieb https://t.co/OPR8twtCLP",
		"created_at": 1446575198,
		"user": {
			"id": "1557883806",
			"name": "MarcoGiesel"
		},
		"retweet_count": 8,
		"id": "661610452523290625",
		"favorite_count": 44
	},
	{
		"text": "Respekt an @dat_olen f\u00fcr den besten \"Deine Muddah\" Spruch seit 8 Jahren :D #rocketminers #rbtv #assihauke",
		"created_at": 1446575212,
		"user": {
			"id": "1164376080",
			"name": "McFranky_"
		},
		"retweet_count": 0,
		"id": "661610508559208448",
		"favorite_count": 1
	},
	{
		"text": "Spontaner Trip nach #Bonn \nKrasse Pimmelei :D \n#spontan #roadtrip #rbtv",
		"created_at": 1446575245,
		"user": {
			"id": "1344894644",
			"name": "dominik_K1803"
		},
		"retweet_count": 0,
		"id": "661610648858677248",
		"favorite_count": 0
	},
	{
		"text": "Hauke muss gleich zu Arno ins B\u00fcro. Sich eine Abmahnung abholen. #rbtv #rocketminers",
		"created_at": 1446575389,
		"user": {
			"id": "40921834",
			"name": "tonino85"
		},
		"retweet_count": 0,
		"id": "661611252989468672",
		"favorite_count": 0
	},
	{
		"text": "@TheRocketBeans #151115 #rbtv Neues Format? Sexy Gaming Clips? https://t.co/bv59Bda5Ui",
		"created_at": 1446575423,
		"user": {
			"id": "3184901781",
			"name": "M3ntalillusi0n"
		},
		"retweet_count": 19,
		"id": "661611394962481152",
		"favorite_count": 148
	},
	{
		"text": "Was geht Leute, seid ihr mit mir down? #rbtv",
		"created_at": 1446575631,
		"user": {
			"id": "3319261849",
			"name": "citynightknight"
		},
		"retweet_count": 0,
		"id": "661612269827186688",
		"favorite_count": 0
	},
	{
		"text": "Bestes Entertainment heute &lt;3\n#rbtv https://t.co/lT2W74ptKB",
		"created_at": 1446575708,
		"user": {
			"id": "2327508482",
			"name": "PeterKonditor"
		},
		"retweet_count": 0,
		"id": "661612590414589952",
		"favorite_count": 5
	},
	{
		"text": "Hey schaut euch mal denn Metroid Live Action Movie an https://t.co/iI4rUUDsk9  Einfach Klasse #rbtv #kinoplus #gameplus",
		"created_at": 1446575751,
		"user": {
			"id": "2981523053",
			"name": "K3nJi87"
		},
		"retweet_count": 0,
		"id": "661612772912971777",
		"favorite_count": 0
	},
	{
		"text": "#rbtv \nhttps://t.co/0xCs5eRi8p\n\nWie cool ist das denn bitte? :D",
		"created_at": 1446575907,
		"user": {
			"id": "1014041096",
			"name": "MartinaF5"
		},
		"retweet_count": 0,
		"id": "661613423785062400",
		"favorite_count": 0
	},
	{
		"text": "@neomagazin Quelle: Internet // @TheRocketBeans #rbtv https://t.co/uyCP6IT3bu",
		"created_at": 1446576051,
		"user": {
			"id": "337083283",
			"name": "PeteBoe"
		},
		"retweet_count": 0,
		"id": "661614027781627904",
		"favorite_count": 1
	},
	{
		"text": "Notiz an mich: Niemals Tweef mit @dat_olen anfangen. Er kontert sonst mit den krassesten Mutterspr\u00fcchen. #rbtv",
		"created_at": 1446576074,
		"user": {
			"id": "3028799397",
			"name": "TechInterMezzo"
		},
		"retweet_count": 1,
		"id": "661614125387239428",
		"favorite_count": 4
	},
	{
		"text": "#rbtv Hey @DerHauge wie gef\u00e4llt dir eigentlich was du da baust?",
		"created_at": 1446576166,
		"user": {
			"id": "624717265",
			"name": "MichaelEngelsk"
		},
		"retweet_count": 0,
		"id": "661614513964392448",
		"favorite_count": 0
	},
	{
		"text": "Marsianer ... Endlich. #Kino #empire #rbtv #kino+",
		"created_at": 1446576201,
		"user": {
			"id": "69879512",
			"name": "Digipatz"
		},
		"retweet_count": 0,
		"id": "661614657115955200",
		"favorite_count": 0
	},
	{
		"text": "#rbtv https://t.co/zOmn05fXoe",
		"created_at": 1446576898,
		"user": {
			"id": "624717265",
			"name": "MichaelEngelsk"
		},
		"retweet_count": 0,
		"id": "661617582684954625",
		"favorite_count": 0
	},
	{
		"text": "Ich glaub ich brauch jetz erst ma ne Woche Urlaub um den ganzen geilen Schei\u00dfe von @TheRocketBeans nach zuholen. #rbtv",
		"created_at": 1446576899,
		"user": {
			"id": "4025291349",
			"name": "Solddtt"
		},
		"retweet_count": 0,
		"id": "661617584568168448",
		"favorite_count": 0
	},
	{
		"text": "@LeSchroeck Perfekte Challenge f\u00fcr dich und #kino+ #rbtv : 66 movie references in one garage. Viel Spa\u00df  https://t.co/gP6iygMUgJ",
		"created_at": 1446577043,
		"user": {
			"id": "827493738",
			"name": "gufte1"
		},
		"retweet_count": 0,
		"id": "661618190880006144",
		"favorite_count": 1
	},
	{
		"text": "Rocketminers ist heute sehr verst\u00f6rend #rbtv",
		"created_at": 1446577211,
		"user": {
			"id": "3319261849",
			"name": "citynightknight"
		},
		"retweet_count": 0,
		"id": "661618895044915203",
		"favorite_count": 0
	},
	{
		"text": "Die Sendung mit @DerHauge war toll toll super toll. #rocketminers #rbtv https://t.co/X1fUMvcIYu",
		"created_at": 1446577474,
		"user": {
			"id": "40921834",
			"name": "tonino85"
		},
		"retweet_count": 1,
		"id": "661619997496709120",
		"favorite_count": 19
	},
	{
		"text": "\"Und wo wohnt der so?\" \ud83d\ude02\u2665 #rbtv #rbnews",
		"created_at": 1446577632,
		"user": {
			"id": "2347700878",
			"name": "Lyannachan"
		},
		"retweet_count": 0,
		"id": "661620661593460736",
		"favorite_count": 0
	},
	{
		"text": "Vergesst #151115 mal ehrlich #91115 wird der shit ! #bohndesliga #rbtv",
		"created_at": 1446577761,
		"user": {
			"id": "610217842",
			"name": "bastistuta_"
		},
		"retweet_count": 0,
		"id": "661621201178087424",
		"favorite_count": 2
	},
	{
		"text": "Die Per\u00fccke steht ihm! XD \u2665 #rbtv #rbnews",
		"created_at": 1446577937,
		"user": {
			"id": "2347700878",
			"name": "Lyannachan"
		},
		"retweet_count": 0,
		"id": "661621941011406850",
		"favorite_count": 1
	},
	{
		"text": "Erst Hauke in Minecraft und jetzt das in den News - was is denn los bei euch? :D #rbtv @TheRocketBeans",
		"created_at": 1446577943,
		"user": {
			"id": "47964721",
			"name": "Animasia"
		},
		"retweet_count": 0,
		"id": "661621963744534529",
		"favorite_count": 1
	},
	{
		"text": "#rbtv #rocketminers #rbnews Alter erst frag ich mich was @DerHauge heute geraucht hat und dann kommen auch noch durchgeknallte News\ud83d\ude04 Hammer",
		"created_at": 1446578076,
		"user": {
			"id": "3526323017",
			"name": "DominikLutz1993"
		},
		"retweet_count": 0,
		"id": "661622521851154433",
		"favorite_count": 1
	},
	{
		"text": "Ich habe gerade mal wieder Tr\u00e4nen gelacht :'D Danke daf\u00fcr @TheRocketBeans #rbtv #rbnews #MobbingamArbeitsplatz https://t.co/V1FVDxMxNf",
		"created_at": 1446578079,
		"user": {
			"id": "94415490",
			"name": "Zockoholiker"
		},
		"retweet_count": 0,
		"id": "661622537000845312",
		"favorite_count": 2
	},
	{
		"text": "#rbtv Hmmm.... Die Musik... Der Hintergrund... Unendliche Weiten... Kann es sein? Mas... Nein, das kann nicht sein. #151115 Oder etwa doch?",
		"created_at": 1446578116,
		"user": {
			"id": "3243941871",
			"name": "notpeepee"
		},
		"retweet_count": 0,
		"id": "661622688721608704",
		"favorite_count": 0
	},
	{
		"text": "https://t.co/6jyKLfB1ZQ #rbtv",
		"created_at": 1446578144,
		"user": {
			"id": "624717265",
			"name": "MichaelEngelsk"
		},
		"retweet_count": 0,
		"id": "661622808699666433",
		"favorite_count": 0
	},
	{
		"text": "gerade die rocket beans #atv app runtergeladen und zum ersten mal #rbnews geschaut...lustig... (c: #rbtv",
		"created_at": 1446578206,
		"user": {
			"id": "449688826",
			"name": "bjoernben"
		},
		"retweet_count": 0,
		"id": "661623068809412609",
		"favorite_count": 1
	},
	{
		"text": "F\u00e4ngt ja super an! \ud83d\ude02 #almostplaily #rbtv",
		"created_at": 1446578206,
		"user": {
			"id": "2347700878",
			"name": "Lyannachan"
		},
		"retweet_count": 0,
		"id": "661623069153370117",
		"favorite_count": 0
	},
	{
		"text": "@Animasia irgendwie scheine ich schon wieder was zu verpassen.... #rbtv",
		"created_at": 1446578991,
		"user": {
			"id": "433269565",
			"name": "stbaf"
		},
		"retweet_count": 0,
		"id": "661626360901869569",
		"favorite_count": 0
	},
	{
		"text": "Soeben wurde im aktuellen #almostplaily der #schummelg\u00e4bel geboren! Endlich kommt die Wahrheit ans Licht! #rbtv",
		"created_at": 1446579419,
		"user": {
			"id": "370029585",
			"name": "TheRocketBeans"
		},
		"retweet_count": 3,
		"id": "661628156852486148",
		"favorite_count": 138
	},
	{
		"text": "\"Mehr links als rechts, das hei\u00dft, ich geh\u00f6re der SPD an.\" Was? #rbtv",
		"created_at": 1446579510,
		"user": {
			"id": "49066780",
			"name": "BakeRolls"
		},
		"retweet_count": 0,
		"id": "661628538517229568",
		"favorite_count": 1
	},
	{
		"text": "Schummel-G\u00e4bel :D #rbtv #almostplaily",
		"created_at": 1446579628,
		"user": {
			"id": "2183990136",
			"name": "SKoch91"
		},
		"retweet_count": 0,
		"id": "661629034661552128",
		"favorite_count": 1
	},
	{
		"text": "#schummelg\u00e4bel #rbtv",
		"created_at": 1446579700,
		"user": {
			"id": "1959404036",
			"name": "HelmutHummer"
		},
		"retweet_count": 0,
		"id": "661629336462716933",
		"favorite_count": 1
	},
	{
		"text": "H\u00e4tten die Cutter da nicht nen Effekt Blitz reinfliegen lassen k\u00f6nnen? \n\n#rbtv #almostdaily",
		"created_at": 1446579709,
		"user": {
			"id": "2389042604",
			"name": "Creeveey"
		},
		"retweet_count": 0,
		"id": "661629372391170049",
		"favorite_count": 2
	},
	{
		"text": "Sehr lustiges #ap besonders mit #schummelgaebel @Colin_Gaebel #rbtv",
		"created_at": 1446579710,
		"user": {
			"id": "88205467",
			"name": "annlp"
		},
		"retweet_count": 0,
		"id": "661629374953750528",
		"favorite_count": 4
	},
	{
		"text": "@TheRocketBeans #almostplaily #rbtv @Colin_Gaebel #schummelg\u00e4bel",
		"created_at": 1446579835,
		"user": {
			"id": "465922337",
			"name": "Frenki_P"
		},
		"retweet_count": 0,
		"id": "661629901825581061",
		"favorite_count": 0
	},
	{
		"text": "richtig gutes AP #rbtv #Schummelg\u00e4bel",
		"created_at": 1446579913,
		"user": {
			"id": "2924808004",
			"name": "NextGenPAM"
		},
		"retweet_count": 0,
		"id": "661630226158460928",
		"favorite_count": 0
	},
	{
		"text": "ob colin wohl mal bei vw gearbeitet hat #schummelg\u00e4bel #rbtv",
		"created_at": 1446579928,
		"user": {
			"id": "1584198696",
			"name": "_Kleini_"
		},
		"retweet_count": 0,
		"id": "661630291921018880",
		"favorite_count": 0
	},
	{
		"text": "@11freunde_bar @oliverpocher Wer dem Trend nicht hinterlaufen will, diskutiert \u00fcber Fu\u00dfball bei #bohndesliga auf @TheRocketBeans! #rbtv",
		"created_at": 1446580140,
		"user": {
			"id": "51476645",
			"name": "game_west"
		},
		"retweet_count": 0,
		"id": "661631178928189440",
		"favorite_count": 2
	},
	{
		"text": "@TheRocketBeans ich Trau mich gar nicht auf dieses \"Gef\u00e4llt mir\" zu klicken :O #rbtv #GefaelltMir #favorisiert",
		"created_at": 1446580480,
		"user": {
			"id": "2873018374",
			"name": "SoNofMarS90"
		},
		"retweet_count": 0,
		"id": "661632606501543937",
		"favorite_count": 0
	},
	{
		"text": "#almostdaily ist das nur bei mir async...? #rbtv",
		"created_at": 1446581219,
		"user": {
			"id": "449688826",
			"name": "bjoernben"
		},
		"retweet_count": 0,
		"id": "661635706528378884",
		"favorite_count": 0
	},
	{
		"text": "#schummelgaebel in die Charts! #rbtv",
		"created_at": 1446581296,
		"user": {
			"id": "43929849",
			"name": "MarkusDancer"
		},
		"retweet_count": 0,
		"id": "661636026830561281",
		"favorite_count": 2
	},
	{
		"text": "#rbtv Wann darf man denn mit dem 24h Fallout Event auf YouTube rechnen?",
		"created_at": 1446581435,
		"user": {
			"id": "3328875735",
			"name": "RGBrain83"
		},
		"retweet_count": 0,
		"id": "661636611881484290",
		"favorite_count": 0
	},
	{
		"text": "Jetzt tauchen @Bimon und @MarcoGiesel wieder tief in die #Overwatch Beta ein. Das rockt doch derbe! #rbtv https://t.co/wJQCTU5AWM",
		"created_at": 1446582110,
		"user": {
			"id": "370029585",
			"name": "TheRocketBeans"
		},
		"retweet_count": 8,
		"id": "661639440784334848",
		"favorite_count": 91
	},
	{
		"text": "@TheRocketBeans Sack Reis, wir glauben an dich! Du richtest den Ton schon &lt;3 #rbtv #zockenmitbohnen",
		"created_at": 1446582117,
		"user": {
			"id": "47964721",
			"name": "Animasia"
		},
		"retweet_count": 0,
		"id": "661639474238119936",
		"favorite_count": 1
	},
	{
		"text": "Yeah Simon #rbtv",
		"created_at": 1446582124,
		"user": {
			"id": "3319261849",
			"name": "citynightknight"
		},
		"retweet_count": 0,
		"id": "661639503069716480",
		"favorite_count": 0
	},
	{
		"text": "It's #TWINKTIME #PS4share #PS4 #destiny #gamingart #rbtv https://t.co/8MxjaUWf3v",
		"created_at": 1446582603,
		"user": {
			"id": "3059913825",
			"name": "voktakh"
		},
		"retweet_count": 0,
		"id": "661641508567822336",
		"favorite_count": 1
	},
	{
		"text": "So langsam entsteht das Heimatdorf Rej\u00f8rsfjall von Klods am Fu\u00dfe des Vulkan von Skarnland. :) #rbtv #RocketMiners https://t.co/VMvKE97zoS",
		"created_at": 1446583607,
		"user": {
			"id": "3382808505",
			"name": "RocketMiners"
		},
		"retweet_count": 1,
		"id": "661645720492113920",
		"favorite_count": 10
	},
	{
		"text": "#dankepaul #rbtv \n#overwatch https://t.co/zzjhhwXahn",
		"created_at": 1446584503,
		"user": {
			"id": "2617857704",
			"name": "__gngr"
		},
		"retweet_count": 0,
		"id": "661649480366862337",
		"favorite_count": 2
	},
	{
		"text": "Europa Report: Realistische gemachte/ausgestattete Sci-Fi Mockumentary, die trotzdem Spannend ist. 7/10 #KinoPlus #rbtv",
		"created_at": 1446586055,
		"user": {
			"id": "2412776252",
			"name": "SchmidtDudley"
		},
		"retweet_count": 0,
		"id": "661655989209440256",
		"favorite_count": 0
	},
	{
		"text": "@TheRocketBeans #rbtv https://t.co/iU3v0F1kKn",
		"created_at": 1446586118,
		"user": {
			"id": "3102430493",
			"name": "Black_Werwulf"
		},
		"retweet_count": 1,
		"id": "661656251588288512",
		"favorite_count": 2
	},
	{
		"text": "Schaaaade! Da waren 3 Punkte m\u00f6glich, trotzdem super gespielt! #rbtv #chambohnsleague #bohndesliga https://t.co/whqsjPscRE",
		"created_at": 1446587811,
		"user": {
			"id": "24653266",
			"name": "marv257"
		},
		"retweet_count": 0,
		"id": "661663354340163585",
		"favorite_count": 1
	},
	{
		"text": "Die #PEGIDA backt EpicsBot #rbtv",
		"created_at": 1446588029,
		"user": {
			"id": "4025619808",
			"name": "ForceOneBot"
		},
		"retweet_count": 0,
		"id": "661664267674984449",
		"favorite_count": 0
	},
	{
		"text": "Der klasse G1 Moment im heutigen Gregott #MoinMoin hat mich irgendwie an Fischmob erinnert! #rbtv #geili https://t.co/IEYPjzPbyT",
		"created_at": 1446589105,
		"user": {
			"id": "1558496984",
			"name": "derJOgelle"
		},
		"retweet_count": 0,
		"id": "661668780695797761",
		"favorite_count": 0
	},
	{
		"text": "Also #Overwatch sieht schon echt nach ner spa\u00dfigen Nummer aus. Mal gucken wer da bald in der Redaktion die Krone aufhat. &gt;:) #rbtv",
		"created_at": 1446589165,
		"user": {
			"id": "370029585",
			"name": "TheRocketBeans"
		},
		"retweet_count": 2,
		"id": "661669035181015040",
		"favorite_count": 63
	},
	{
		"text": "@EtienneToGo Es bleibt spannend! #rbtv #pokemon #Abgasskandal https://t.co/FHo7lElmLC",
		"created_at": 1446589470,
		"user": {
			"id": "365061054",
			"name": "byro90"
		},
		"retweet_count": 0,
		"id": "661670311411245056",
		"favorite_count": 1
	},
	{
		"text": "Hard Mode Raid at 7:15 EST! Come hang out on stream!\nhttps://t.co/YwlbylKeTf\n#destiny #takenking #kingsfall #RBTV",
		"created_at": 1446589531,
		"user": {
			"id": "3477434121",
			"name": "RossBossTV"
		},
		"retweet_count": 0,
		"id": "661670567804870657",
		"favorite_count": 0
	},
	{
		"text": "@bimon Wird es \"Superwarten 3D\" mit Singleplayer und 4er Coop geben? #overwatch #rbtv",
		"created_at": 1446590109,
		"user": {
			"id": "2848409806",
			"name": "DocTrivia"
		},
		"retweet_count": 0,
		"id": "661672994696220673",
		"favorite_count": 0
	}
]